Workbook

Sheet Guide
A1: IFRS 17 risk adjustment: cost of capital method, step by step
A2: A learning workbook. All numbers are illustrative (Solvency II-style stresses), not any company's calibration.
A4: How the RA is built in this workbook
A5: 1. Inputs: assumptions for a term assurance group and an immediate annuity group, the stresses, the correlation matrix and the cost of capital.
A6: 2. Term and Annuity: per-policy BEL by backward recursion, on best-estimate and on each stressed basis. Capital for a risk at time t = in-force at t × (stressed BEL − best-estimate BEL), with the stress applied from t onwards.
A7: 3. Capital: combines the risks each year with the correlation matrix (diversified), compares with each group on its own (standalone), and allocates the diversified capital back to the groups two ways: Euler (by each risk's marginal contribution) and proportional to standalone capital. Euler can give a group a small negative share when its risk hedges the other group (see the term group near the end of its term).
A8: 4. RA: RA(t) = CoC × Capital(t) × v + v × RA(t+1). This is the PV of the cost of holding capital until the business runs off (IFRS 17 para 37, B86–B92).
A9: 5. Factor method: calibrates one factor per risk at t = 0 and rebuilds the RA from exposures only. Compare it with the full method to see the approximation error.
A10: 6. Confidence: the implied confidence level for the para 119 disclosure, in a one-year view and a run-off view. The gap between them is itself a lesson (see the note on that sheet).
A11: 7. Summary: the key results and checks in one place.
A13: Timing conventions
A14: Premiums and expenses at the start of the year; death claims and annuity payments at the end of the year; lapses at the end of the year after deaths. Flat discount rate.
... A26: 6. Add the Solvency II expense inflation stress (+1% a year) to both product sheets. Hint: it needs the stress to start at the valuation date.

Sheet Summary
A1: Summary
A3: Alternative cost of capital rate | B3: 0.0475 | C3: Solvency II rate from 2027; used in the last column below
B5: Term | C5: Annuity | D5: Total | E5: RA at alternative CoC
A6: BEL at t = 0 | B6: =Term!T6 -> -12996781 | C6: =Annuity!N6 -> 61049166 | D6: =B6+C6 -> 48052384
A7: Capital at t = 0 (standalone) | B7: =Capital!M6 -> 3468959 | C7: =Capital!N6 -> 3054434 | D7: =B7+C7 -> 6523393
A8: Capital at t = 0 (diversified, allocated) | B8: =Capital!U6 -> 2497051.1 | C8: =Capital!V6 -> 1879136.7 | D8: =Capital!L6 -> 4376187.8
A9: RA at t = 0 (standalone) | B9: =RA!E6 -> 2120324.1 | C9: =RA!F6 -> 3343105.4 | D9: =B9+C9 -> 5463429.5 | E9: =D9*$B$3/Inputs!$B$5 -> 4325215
A10: RA at t = 0 (diversified, allocated) | B10: =RA!C6 -> 1221599 | C10: =RA!D6 -> 2679071.8 | D10: =RA!B6 -> 3900670.8 | E10: =D10*$B$3/Inputs!$B$5 -> 3088031.1
A11: RA at t = 0 (diversified, proportional) | B11: =RA!J6 -> 1422131 | C11: =RA!K6 -> 2478539.8 | D11: =B11+C11 -> 3900670.8
A12: Diversification benefit on RA | B12: =IF(B9=0,0,1-B10/B9) -> 0.42386213 | C12: =IF(C9=0,0,1-C10/C9) -> 0.19862777 | D12: =IF(D9=0,0,1-D10/D9) -> 0.28603987
A13: RA as % of BEL (diversified) | B13: =IF(B6=0,0,B10/ABS(B6)) -> 0.093992425 | C13: =IF(C6=0,0,C10/C6) -> 0.04388384
A14: RA by factor method | D14: ='Factor method'!H9 -> 2704841.6
A15: Factor method error | D15: ='Factor method'!H11 -> -0.30657014
A16: Implied confidence level: run-off view | D16: =Confidence!F12 -> 0.77051734
A17: Implied confidence level: one-year view | D17: =Confidence!F5 -> 0.98916033
A18: Implied confidence level, factor method (run-off view) | D18: ='Confidence Factor method'!F12 -> 0.69620641
A19: Checks (all should be 0)
A20: Term BEL identity (Σ |error|) | D20: =SUMPRODUCT(ABS(Term!AB6:AB25)) -> 1.1795009e-12
A21: Euler allocation adds up (Σ |error|) | D21: =SUMPRODUCT(ABS(Capital!W6:W50)) -> 0
A22: Allocated RAs add up (Σ |error|) | D22: =SUMPRODUCT(ABS(RA!I6:I50)) -> 0
A24: Note: the term BEL is negative because future premiums exceed expected claims and expenses (a profitable group).

Sheet Inputs
A1: Inputs
A2: Amounts in EUR. Blue cells can be changed.
A4: General
A5: Cost of capital rate | B5: 0.06 | C5: Solvency II Art. 39 (falls to 4.75% from 2027)
A6: Discount rate (flat) | B6: 0.03 | C6: Simplified risk-free rate
A7: Mortality basis (Gompertz-Makeham)
A8: A | B8: 0.00022 | C8: q = 1 − exp(−(A + B × C^age))
A9: B | B9: 2.7e-06
A10: C | B10: 1.124
A12: Term assurance group
A13: Number of policies | B13: 10000
A14: Age at start | B14: 40
A15: Term (years) | B15: 20 | C15: Projection rows cover 20 years
A16: Sum assured per policy | B16: 200000
A17: Annual premium per policy | B17: 400 | C17: Paid at start of year
A18: Expense per policy, year 1 | B18: 60
A19: Expense inflation | B19: 0.03 | C19: Used for both groups
A20: Lapse rate | B20: 0.05
A21: Mortality multiplier | B21: 1 | C21: × base table
A23: Immediate annuity group
A24: Number of policies | B24: 300
A25: Age at start | B25: 65 | C25: Projected to age 110
A26: Annual annuity per policy | B26: 12000 | C26: Paid at end of year to survivors
A27: Expense per policy, year 1 | B27: 90
A28: Mortality multiplier | B28: 0.75 | C28: Annuitants live longer than the base table
A30: Stresses (Solvency II-style)
A31: Mortality: change in q (term) | B31: 0.15 | C31: SII Art. 137: +15%
A32: Longevity: change in q (annuity) | B32: -0.2 | C32: SII Art. 138: −20%
A33: Lapse up: change in lapse rate | B33: 0.5 | C33: SII Art. 142: +50%, capped at 100%
A34: Lapse down: change in lapse rate | B34: -0.5 | C34: SII Art. 142: −50% ...
A35: Lapse down: maximum absolute fall | B35: 0.2 | C35: ... capped at a fall of 20 percentage points
A36: Expense level: change | B36: 0.1 | C36: SII Art. 140: +10% (inflation stress left as exercise 6)
A38: Correlation between risks (Solvency II Art. 136)
B39: Mortality | C39: Longevity | D39: Lapse | E39: Expense
A40: Mortality | B40: 1 | C40: -0.25 | D40: 0 | E40: 0.25
A41: Longevity | B41: -0.25 | C41: 1 | D41: 0.25 | E41: 0.25
A42: Lapse | B42: 0 | C42: 0.25 | D42: 1 | E42: 0.5
A43: Expense | B43: 0.25 | C43: 0.25 | D43: 0.5 | E43: 1

Sheet Term
A1: Term assurance group: per-policy BEL on each basis, capital and exposures
A2: Per-policy BEL(t) = expense − premium + q × SA × v + (1 − q)(1 − lapse) × v × BEL(t+1). | H2: Capital = in-force × (stressed BEL − best-estimate BEL), floored at 0.
A3: Columns C–H: best estimate. I–P: stressed bases. Q–S: per-policy PVs used as exposures. T–AA: totals for the group.
A5: t | B5: Age | C5: q (best est.) | D5: Lapse rate | E5: Premium per policy | F5: Expense per policy | G5: In-force at start of year | H5: BEL per policy: best estimate | I5: q (mortality stress) | J5: BEL per policy: mortality stress | K5: Lapse (up stress) | L5: BEL per policy: lapse up | M5: Lapse (down stress) | N5: BEL per policy: lapse down | O5: Expense (stressed) | P5: BEL per policy: expense stress | Q5: PV future claims per policy | R5: PV future expenses per policy | S5: PV future premiums per policy | T5: BEL total (group) | U5: Capital: mortality | V5: Capital: lapse (worst of up/down) | W5: Capital: expense | X5: Exposure: sum assured in force | Y5: Exposure: PV future claims | Z5: Exposure: PV future profits | AA5: Exposure: PV future expenses | AB5: Check: BEL − (claims + expenses − premiums)
A6: 0 | B6: =Inputs!$B$14+A6 -> 40 | C6: =MIN(Inputs!$B$21*(1-EXP(-(Inputs!$B$8+Inputs!$B$9*Inputs!$B$10^B6))),1) -> 0.00050961528 | D6: =Inputs!$B$20 -> 0.05 | E6: =Inputs!$B$17 -> 400 | F6: =Inputs!$B$18*(1+Inputs!$B$19)^A6 -> 60 | G6: =Inputs!$B$13 -> 10000 | H6: =F6-E6+C6*Inputs!$B$16*(1/(1+Inputs!$B$6))+(1-C6)*(1-D6)*(1/(1+Inputs!$B$6))*H7 -> -1299.6781 | I6: =MIN(C6*(1+Inputs!$B$31),1) -> 0.00058605757 | J6: =F6-E6+I6*Inputs!$B$16*(1/(1+Inputs!$B$6))+(1-I6)*(1-D6)*(1/(1+Inputs!$B$6))*J7 -> -994.12088 | K6: =MIN(D6*(1+Inputs!$B$33),1) -> 0.075 | L6: =F6-E6+C6*Inputs!$B$16*(1/(1+Inputs!$B$6))+(1-C6)*(1-K6)*(1/(1+Inputs!$B$6))*L7 -> -1233.4987 | M6: =MAX(D6*(1+Inputs!$B$34),D6-Inputs!$B$35) -> 0.025 | N6: =F6-E6+C6*Inputs!$B$16*(1/(1+Inputs!$B$6))+(1-C6)*(1-M6)*(1/(1+Inputs!$B$6))*N7 -> -1348.0006 | O6: =F6*(1+Inputs!$B$36) -> 66 | P6: =O6-E6+C6*Inputs!$B$16*(1/(1+Inputs!$B$6))+(1-C6)*(1-D6)*(1/(1+Inputs!$B$6))*P7 -> -1223.207 | Q6: =C6*Inputs!$B$16*(1/(1+Inputs!$B$6))+(1-C6)*(1-D6)*(1/(1+Inputs!$B$6))*Q7 -> 2040.0115 | R6: =F6+(1-C6)*(1-D6)*(1/(1+Inputs!$B$6))*R7 -> 764.71177 | S6: =E6+(1-C6)*(1-D6)*(1/(1+Inputs!$B$6))*S7 -> 4104.4014 | T6: =G6*H6 -> -12996781 | U6: =G6*MAX(J6-H6,0) -> 3055572.5 | V6: =G6*MAX(L6-H6,N6-H6,0) -> 661794.1 | W6: =G6*MAX(P6-H6,0) -> 764711.77 | X6: =G6*Inputs!$B$16 -> 2000000000 | Y6: =G6*Q6 -> 20400115 | Z6: =G6*MAX(S6-Q6-R6,0) -> 12996781 | AA6: =G6*R6 -> 7647117.7 | AB6: =H6-(Q6+R6-S6) -> 0
A7: 1 | B7: =Inputs!$B$14+A7 -> 41 | C7: =MIN(Inputs!$B$21*(1-EXP(-(Inputs!$B$8+Inputs!$B$9*Inputs!$B$10^B7))),1) -> 0.00054552472 | D7: =Inputs!$B$20 -> 0.05 | E7: =Inputs!$B$17 -> 400 | F7: =Inputs!$B$18*(1+Inputs!$B$19)^A7 -> 61.8 | G7: =G6*(1-C6)*(1-D6) -> 9495.1587 | H7: =F7-E7+C7*Inputs!$B$16*(1/(1+Inputs!$B$6))+(1-C7)*(1-D7)*(1/(1+Inputs!$B$6))*H8 -> -1148.3658 | I7: =MIN(C7*(1+Inputs!$B$31),1) -> 0.00062735343 | J7: =F7-E7+I7*Inputs!$B$16*(1/(1+Inputs!$B$6))+(1-I7)*(1-D7)*(1/(1+Inputs!$B$6))*J8 -> -833.07352 | K7: =MIN(D7*(1+Inputs!$B$33),1) -> 0.075 | L7: =F7-E7+C7*Inputs!$B$16*(1/(1+Inputs!$B$6))+(1-C7)*(1-K7)*(1/(1+Inputs!$B$6))*L8 -> -1105.6735 | M7: =MAX(D7*(1+Inputs!$B$34),D7-Inputs!$B$35) -> 0.025 | N7: =F7-E7+C7*Inputs!$B$16*(1/(1+Inputs!$B$6))+(1-C7)*(1-M7)*(1/(1+Inputs!$B$6))*N8 -> -1169.9949 | O7: =F7*(1+Inputs!$B$36) -> 67.98 | P7: =O7-E7+C7*Inputs!$B$16*(1/(1+Inputs!$B$6))+(1-C7)*(1-D7)*(1/(1+Inputs!$B$6))*P8 -> -1071.9212 | Q7: =C7*Inputs!$B$16*(1/(1+Inputs!$B$6))+(1-C7)*(1-D7)*(1/(1+Inputs!$B$6))*Q8 -> 2105.5875 | R7: =F7+(1-C7)*(1-D7)*(1/(1+Inputs!$B$6))*R8 -> 764.4455 | S7: =E7+(1-C7)*(1-D7)*(1/(1+Inputs!$B$6))*S8 -> 4018.3988 | T7: =G7*H7 -> -10903915 | U7: =G7*MAX(J7-H7,0) -> 2993750.1 | V7: =G7*MAX(L7-H7,N7-H7,0) -> 405370.43 | W7: =G7*MAX(P7-H7,0) -> 725853.13 | X7: =G7*Inputs!$B$16 -> 1.8990317e+09 | Y7: =G7*Q7 -> 19992887 | Z7: =G7*MAX(S7-Q7-R7,0) -> 10903915 | AA7: =G7*R7 -> 7258531.3 | AB7: =H7-(Q7+R7-S7) -> 0
A8: 2 | B8: =Inputs!$B$14+A8 -> 42 | C8: =MIN(Inputs!$B$21*(1-EXP(-(Inputs!$B$8+Inputs!$B$9*Inputs!$B$10^B8))),1) -> 0.0005858854 | D8: =Inputs!$B$20 -> 0.05 | E8: =Inputs!$B$17 -> 400 | F8: =Inputs!$B$18*(1+Inputs!$B$19)^A8 -> 63.654 | G8: =G7*(1-C7)*(1-D7) -> 9015.4799 | H8: =F8-E8+C8*Inputs!$B$16*(1/(1+Inputs!$B$6))+(1-C8)*(1-D8)*(1/(1+Inputs!$B$6))*H9 -> -993.77971 | I8: =MIN(C8*(1+Inputs!$B$31),1) -> 0.00067376821 | J8: =F8-E8+I8*Inputs!$B$16*(1/(1+Inputs!$B$6))+(1-I8)*(1-D8)*(1/(1+Inputs!$B$6))*J9 -> -669.04121 | K8: =MIN(D8*(1+Inputs!$B$33),1) -> 0.075 | L8: =F8-E8+C8*Inputs!$B$16*(1/(1+Inputs!$B$6))+(1-C8)*(1-K8)*(1/(1+Inputs!$B$6))*L9 -> -973.07419 | M8: =MAX(D8*(1+Inputs!$B$34),D8-Inputs!$B$35) -> 0.025 | N8: =F8-E8+C8*Inputs!$B$16*(1/(1+Inputs!$B$6))+(1-C8)*(1-M8)*(1/(1+Inputs!$B$6))*N9 -> -991.15991 | O8: =F8*(1+Inputs!$B$36) -> 70.0194 | P8: =O8-E8+C8*Inputs!$B$16*(1/(1+Inputs!$B$6))+(1-C8)*(1-D8)*(1/(1+Inputs!$B$6))*P9 -> -917.55657 | Q8: =C8*Inputs!$B$16*(1/(1+Inputs!$B$6))+(1-C8)*(1-D8)*(1/(1+Inputs!$B$6))*Q9 -> 2169.2362 | R8: =F8+(1-C8)*(1-D8)*(1/(1+Inputs!$B$6))*R9 -> 762.23146 | S8: =E8+(1-C8)*(1-D8)*(1/(1+Inputs!$B$6))*S9 -> 3925.2474 | T8: =G8*H8 -> -8959401 | U8: =G8*MAX(J8-H8,0) -> 2927673.4 | V8: =G8*MAX(L8-H8,N8-H8,0) -> 186670.21 | W8: =G8*MAX(P8-H8,0) -> 687188.24 | X8: =G8*Inputs!$B$16 -> 1.803096e+09 | Y8: =G8*Q8 -> 19556705 | Z8: =G8*MAX(S8-Q8-R8,0) -> 8959401 | AA8: =G8*R8 -> 6871882.4 | AB8: =H8-(Q8+R8-S8) -> 0
A9: 3 | B9: =Inputs!$B$14+A9 -> 43 | C9: =MIN(Inputs!$B$21*(1-EXP(-(Inputs!$B$8+Inputs!$B$9*Inputs!$B$10^B9))),1) -> 0.00063124886 | D9: =Inputs!$B$20 -> 0.05 | E9: =Inputs!$B$17 -> 400 | F9: =Inputs!$B$18*(1+Inputs!$B$19)^A9 -> 65.56362 | G9: =G8*(1-C8)*(1-D8) -> 8559.6879 | H9: =F9-E9+C9*Inputs!$B$16*(1/(1+Inputs!$B$6))+(1-C9)*(1-D9)*(1/(1+Inputs!$B$6))*H10 -> -836.63102 | I9: =MIN(C9*(1+Inputs!$B$31),1) -> 0.00072593619 | J9: =F9-E9+I9*Inputs!$B$16*(1/(1+Inputs!$B$6))+(1-I9)*(1-D9)*(1/(1+Inputs!$B$6))*J10 -> -502.89642 | K9: =MIN(D9*(1+Inputs!$B$33),1) -> 0.075 | L9: =F9-E9+C9*Inputs!$B$16*(1/(1+Inputs!$B$6))+(1-C9)*(1-K9)*(1/(1+Inputs!$B$6))*L10 -> -836.17327 | M9: =MAX(D9*(1+Inputs!$B$34),D9-Inputs!$B$35) -> 0.025 | N9: =F9-E9+C9*Inputs!$B$16*(1/(1+Inputs!$B$6))+(1-C9)*(1-M9)*(1/(1+Inputs!$B$6))*N10 -> -812.40973 | O9: =F9*(1+Inputs!$B$36) -> 72.119982 | P9: =O9-E9+C9*Inputs!$B$16*(1/(1+Inputs!$B$6))+(1-C9)*(1-D9)*(1/(1+Inputs!$B$6))*P10 -> -760.84611 | Q9: =C9*Inputs!$B$16*(1/(1+Inputs!$B$6))+(1-C9)*(1-D9)*(1/(1+Inputs!$B$6))*Q10 -> 2229.8709 | R9: =F9+(1-C9)*(1-D9)*(1/(1+Inputs!$B$6))*R10 -> 757.84905 | S9: =E9+(1-C9)*(1-D9)*(1/(1+Inputs!$B$6))*S10 -> 3824.3509 | T9: =G9*H9 -> -7161300.4 | U9: =G9*MAX(J9-H9,0) -> 2856664 | V9: =G9*MAX(L9-H9,N9-H9,0) -> 207326.63 | W9: =G9*MAX(P9-H9,0) -> 648695.13 | X9: =G9*Inputs!$B$16 -> 1.7119376e+09 | Y9: =G9*Q9 -> 19086999 | Z9: =G9*MAX(S9-Q9-R9,0) -> 7161300.4 | AA9: =G9*R9 -> 6486951.3 | AB9: =H9-(Q9+R9-S9) -> 0
A10: 4 | B10: =Inputs!$B$14+A10 -> 44 | C10: =MIN(Inputs!$B$21*(1-EXP(-(Inputs!$B$8+Inputs!$B$9*Inputs!$B$10^B10))),1) -> 0.00068223493 | D10: =Inputs!$B$20 -> 0.05 | E10: =Inputs!$B$17 -> 400 | F10: =Inputs!$B$18*(1+Inputs!$B$19)^A10 -> 67.530529 | G10: =G9*(1-C9)*(1-D9) -> 8126.5704 | H10: =F10-E10+C10*Inputs!$B$16*(1/(1+Inputs!$B$6))+(1-C10)*(1-D10)*(1/(1+Inputs!$B$6))*H11 -> -677.80707 | I10: =MIN(C10*(1+Inputs!$B$31),1) -> 0.00078457017 | J10: =F10-E10+I10*Inputs!$B$16*(1/(1+Inputs!$B$6))+(1-I10)*(1-D10)*(1/(1+Inputs!$B$6))*J11 -> -335.71854 | K10: =MIN(D10*(1+Inputs!$B$33),1) -> 0.075 | L10: =F10-E10+C10*Inputs!$B$16*(1/(1+Inputs!$B$6))+(1-C10)*(1-K10)*(1/(1+Inputs!$B$6))*L11 -> -695.61616 | M10: =MAX(D10*(1+Inputs!$B$34),D10-Inputs!$B$35) -> 0.025 | N10: =F10-E10+C10*Inputs!$B$16*(1/(1+Inputs!$B$6))+(1-C10)*(1-M10)*(1/(1+Inputs!$B$6))*N11 -> -634.82363 | O10: =F10*(1+Inputs!$B$36) -> 74.283581 | P10: =O10-E10+C10*Inputs!$B$16*(1/(1+Inputs!$B$6))+(1-C10)*(1-D10)*(1/(1+Inputs!$B$6))*P11 -> -602.70135 | Q10: =C10*Inputs!$B$16*(1/(1+Inputs!$B$6))+(1-C10)*(1-D10)*(1/(1+Inputs!$B$6))*Q11 -> 2286.1981 | R10: =F10+(1-C10)*(1-D10)*(1/(1+Inputs!$B$6))*R11 -> 751.05725 | S10: =E10+(1-C10)*(1-D10)*(1/(1+Inputs!$B$6))*S11 -> 3715.0625 | T10: =G10*H10 -> -5508246.9 | U10: =G10*MAX(J10-H10,0) -> 2780006.6 | V10: =G10*MAX(L10-H10,N10-H10,0) -> 349307.98 | W10: =G10*MAX(P10-H10,0) -> 610351.96 | X10: =G10*Inputs!$B$16 -> 1.6253141e+09 | Y10: =G10*Q10 -> 18578950 | Z10: =G10*MAX(S10-Q10-R10,0) -> 5508246.9 | AA10: =G10*R10 -> 6103519.6 | AB10: =H10-(Q10+R10-S10) -> 0
A11: 5 | B11: =Inputs!$B$14+A11 -> 45 | C11: =MIN(Inputs!$B$21*(1-EXP(-(Inputs!$B$8+Inputs!$B$9*Inputs!$B$10^B11))),1) -> 0.00073954016 | D11: =Inputs!$B$20 -> 0.05 | E11: =Inputs!$B$17 -> 400 | F11: =Inputs!$B$18*(1+Inputs!$B$19)^A11 -> 69.556444 | G11: =G10*(1-C10)*(1-D10) -> 7714.9749 | H11: =F11-E11+C11*Inputs!$B$16*(1/(1+Inputs!$B$6))+(1-C11)*(1-D11)*(1/(1+Inputs!$B$6))*H12 -> -518.40074 | I11: =MIN(C11*(1+Inputs!$B$31),1) -> 0.00085047119 | J11: =F11-E11+I11*Inputs!$B$16*(1/(1+Inputs!$B$6))+(1-I11)*(1-D11)*(1/(1+Inputs!$B$6))*J12 -> -168.82779 | K11: =MIN(D11*(1+Inputs!$B$33),1) -> 0.075 | L11: =F11-E11+C11*Inputs!$B$16*(1/(1+Inputs!$B$6))+(1-C11)*(1-K11)*(1/(1+Inputs!$B$6))*L12 -> -552.25577 | M11: =MAX(D11*(1+Inputs!$B$34),D11-Inputs!$B$35) -> 0.025 | N11: =F11-E11+C11*Inputs!$B$16*(1/(1+Inputs!$B$6))+(1-C11)*(1-M11)*(1/(1+Inputs!$B$6))*N12 -> -459.66926 | O11: =F11*(1+Inputs!$B$36) -> 76.512089 | P11: =O11-E11+C11*Inputs!$B$16*(1/(1+Inputs!$B$6))+(1-C11)*(1-D11)*(1/(1+Inputs!$B$6))*P12 -> -444.24146 | Q11: =C11*Inputs!$B$16*(1/(1+Inputs!$B$6))+(1-C11)*(1-D11)*(1/(1+Inputs!$B$6))*Q12 -> 2336.6859 | R11: =F11+(1-C11)*(1-D11)*(1/(1+Inputs!$B$6))*R12 -> 741.59281 | S11: =E11+(1-C11)*(1-D11)*(1/(1+Inputs!$B$6))*S12 -> 3596.6794 | T11: =G11*H11 -> -3999448.7 | U11: =G11*MAX(J11-H11,0) -> 2696946.5 | V11: =G11*MAX(L11-H11,N11-H11,0) -> 453111.87 | W11: =G11*MAX(P11-H11,0) -> 572136.99 | X11: =G11*Inputs!$B$16 -> 1.542995e+09 | Y11: =G11*Q11 -> 18027473 | Z11: =G11*MAX(S11-Q11-R11,0) -> 3999448.7 | AA11: =G11*R11 -> 5721369.9 | AB11: =H11-(Q11+R11-S11) -> 0
A12: 6 | B12: =Inputs!$B$14+A12 -> 46 | C12: =MIN(Inputs!$B$21*(1-EXP(-(Inputs!$B$8+Inputs!$B$9*Inputs!$B$10^B12))),1) -> 0.00080394732 | D12: =Inputs!$B$20 -> 0.05 | E12: =Inputs!$B$17 -> 400 | F12: =Inputs!$B$18*(1+Inputs!$B$19)^A12 -> 71.643138 | G12: =G11*(1-C11)*(1-D11) -> 7323.8059 | H12: =F12-E12+C12*Inputs!$B$16*(1/(1+Inputs!$B$6))+(1-C12)*(1-D12)*(1/(1+Inputs!$B$6))*H13 -> -359.74387 | I12: =MIN(C12*(1+Inputs!$B$31),1) -> 0.00092453942 | J12: =F12-E12+I12*Inputs!$B$16*(1/(1+Inputs!$B$6))+(1-I12)*(1-D12)*(1/(1+Inputs!$B$6))*J13 -> -3.8243076 | K12: =MIN(D12*(1+Inputs!$B$33),1) -> 0.075 | L12: =F12-E12+C12*Inputs!$B$16*(1/(1+Inputs!$B$6))+(1-C12)*(1-K12)*(1/(1+Inputs!$B$6))*L13 -> -407.1926 | M12: =MAX(D12*(1+Inputs!$B$34),D12-Inputs!$B$35) -> 0.025 | N12: =F12-E12+C12*Inputs!$B$16*(1/(1+Inputs!$B$6))+(1-C12)*(1-M12)*(1/(1+Inputs!$B$6))*N13 -> -288.42921 | O12: =F12*(1+Inputs!$B$36) -> 78.807452 | P12: =O12-E12+C12*Inputs!$B$16*(1/(1+Inputs!$B$6))+(1-C12)*(1-D12)*(1/(1+Inputs!$B$6))*P13 -> -286.82705 | Q12: =C12*Inputs!$B$16*(1/(1+Inputs!$B$6))+(1-C12)*(1-D12)*(1/(1+Inputs!$B$6))*Q13 -> 2379.5265 | R12: =F12+(1-C12)*(1-D12)*(1/(1+Inputs!$B$6))*R13 -> 729.16815 | S12: =E12+(1-C12)*(1-D12)*(1/(1+Inputs!$B$6))*S13 -> 3468.4385 | T12: =G12*H12 -> -2634694.3 | U12: =G12*MAX(J12-H12,0) -> 2606685.8 | V12: =G12*MAX(L12-H12,N12-H12,0) -> 522294.69 | W12: =G12*MAX(P12-H12,0) -> 534028.6 | X12: =G12*Inputs!$B$16 -> 1.4647612e+09 | Y12: =G12*Q12 -> 17427190 | Z12: =G12*MAX(S12-Q12-R12,0) -> 2634694.3 | AA12: =G12*R12 -> 5340286 | AB12: =H12-(Q12+R12-S12) -> 5.6843419e-13
A13: 7 | B13: =Inputs!$B$14+A13 -> 47 | C13: =MIN(Inputs!$B$21*(1-EXP(-(Inputs!$B$8+Inputs!$B$9*Inputs!$B$10^B13))),1) -> 0.00087633602 | D13: =Inputs!$B$20 -> 0.05 | E13: =Inputs!$B$17 -> 400 | F13: =Inputs!$B$18*(1+Inputs!$B$19)^A13 -> 73.792432 | G13: =G12*(1-C12)*(1-D12) -> 6952.022 | H13: =F13-E13+C13*Inputs!$B$16*(1/(1+Inputs!$B$6))+(1-C13)*(1-D13)*(1/(1+Inputs!$B$6))*H14 -> -203.44575 | I13: =MIN(C13*(1+Inputs!$B$31),1) -> 0.0010077864 | J13: =F13-E13+I13*Inputs!$B$16*(1/(1+Inputs!$B$6))+(1-I13)*(1-D13)*(1/(1+Inputs!$B$6))*J14 -> 157.36723 | K13: =MIN(D13*(1+Inputs!$B$33),1) -> 0.075 | L13: =F13-E13+C13*Inputs!$B$16*(1/(1+Inputs!$B$6))+(1-C13)*(1-K13)*(1/(1+Inputs!$B$6))*L14 -> -261.8216 | M13: =MAX(D13*(1+Inputs!$B$34),D13-Inputs!$B$35) -> 0.025 | N13: =F13-E13+C13*Inputs!$B$16*(1/(1+Inputs!$B$6))+(1-C13)*(1-M13)*(1/(1+Inputs!$B$6))*N14 -> -122.83104 | O13: =F13*(1+Inputs!$B$36) -> 81.171675 | P13: =O13-E13+C13*Inputs!$B$16*(1/(1+Inputs!$B$6))+(1-C13)*(1-D13)*(1/(1+Inputs!$B$6))*P14 -> -132.09884 | Q13: =C13*Inputs!$B$16*(1/(1+Inputs!$B$6))+(1-C13)*(1-D13)*(1/(1+Inputs!$B$6))*Q14 -> 2412.5952 | R13: =F13+(1-C13)*(1-D13)*(1/(1+Inputs!$B$6))*R14 -> 713.46913 | S13: =E13+(1-C13)*(1-D13)*(1/(1+Inputs!$B$6))*S14 -> 3329.5101 | T13: =G13*H13 -> -1414359.3 | U13: =G13*MAX(J13-H13,0) -> 2508379.8 | V13: =G13*MAX(L13-H13,N13-H13,0) -> 560435.22 | W13: =G13*MAX(P13-H13,0) -> 496005.31 | X13: =G13*Inputs!$B$16 -> 1.3904044e+09 | Y13: =G13*Q13 -> 16772415 | Z13: =G13*MAX(S13-Q13-R13,0) -> 1414359.3 | AA13: =G13*R13 -> 4960053.1 | AB13: =H13-(Q13+R13-S13) -> 0
A14: 8 | B14: =Inputs!$B$14+A14 -> 48 | C14: =MIN(Inputs!$B$21*(1-EXP(-(Inputs!$B$8+Inputs!$B$9*Inputs!$B$10^B14))),1) -> 0.00095769465 | D14: =Inputs!$B$20 -> 0.05 | E14: =Inputs!$B$17 -> 400 | F14: =Inputs!$B$18*(1+Inputs!$B$19)^A14 -> 76.006205 | G14: =G13*(1-C13)*(1-D13) -> 6598.6332 | H14: =F14-E14+C14*Inputs!$B$16*(1/(1+Inputs!$B$6))+(1-C14)*(1-D14)*(1/(1+Inputs!$B$6))*H15 -> -51.437216 | I14: =MIN(C14*(1+Inputs!$B$31),1) -> 0.0011013488 | J14: =F14-E14+I14*Inputs!$B$16*(1/(1+Inputs!$B$6))+(1-I14)*(1-D14)*(1/(1+Inputs!$B$6))*J15 -> 312.4462 | K14: =MIN(D14*(1+Inputs!$B$33),1) -> 0.075 | L14: =F14-E14+C14*Inputs!$B$16*(1/(1+Inputs!$B$6))+(1-C14)*(1-K14)*(1/(1+Inputs!$B$6))*L15 -> -117.88672 | M14: =MAX(D14*(1+Inputs!$B$34),D14-Inputs!$B$35) -> 0.025 | N14: =F14-E14+C14*Inputs!$B$16*(1/(1+Inputs!$B$6))+(1-C14)*(1-M14)*(1/(1+Inputs!$B$6))*N15 -> 35.118586 | O14: =F14*(1+Inputs!$B$36) -> 83.606825 | P14: =O14-E14+C14*Inputs!$B$16*(1/(1+Inputs!$B$6))+(1-C14)*(1-D14)*(1/(1+Inputs!$B$6))*P15 -> 17.978036 | Q14: =C14*Inputs!$B$16*(1/(1+Inputs!$B$6))+(1-C14)*(1-D14)*(1/(1+Inputs!$B$6))*Q15 -> 2433.4018 | R14: =F14+(1-C14)*(1-D14)*(1/(1+Inputs!$B$6))*R15 -> 694.15252 | S14: =E14+(1-C14)*(1-D14)*(1/(1+Inputs!$B$6))*S15 -> 3178.9915 | T14: =G14*H14 -> -339415.32 | U14: =G14*MAX(J14-H14,0) -> 2401133.2 | V14: =G14*MAX(L14-H14,N14-H14,0) -> 571149.99 | W14: =G14*MAX(P14-H14,0) -> 458045.79 | X14: =G14*Inputs!$B$16 -> 1.3197266e+09 | Y14: =G14*Q14 -> 16057126 | Z14: =G14*MAX(S14-Q14-R14,0) -> 339415.32 | AA14: =G14*R14 -> 4580457.9 | AB14: =H14-(Q14+R14-S14) -> -2.1316282e-13
A15: 9 | B15: =Inputs!$B$14+A15 -> 49 | C15: =MIN(Inputs!$B$21*(1-EXP(-(Inputs!$B$8+Inputs!$B$9*Inputs!$B$10^B15))),1) -> 0.0010491338 | D15: =Inputs!$B$20 -> 0.05 | E15: =Inputs!$B$17 -> 400 | F15: =Inputs!$B$18*(1+Inputs!$B$19)^A15 -> 78.286391 | G15: =G14*(1-C14)*(1-D14) -> 6262.6981 | H15: =F15-E15+C15*Inputs!$B$16*(1/(1+Inputs!$B$6))+(1-C15)*(1-D15)*(1/(1+Inputs!$B$6))*H16 -> 93.978788 | I15: =MIN(C15*(1+Inputs!$B$31),1) -> 0.0012065039 | J15: =F15-E15+I15*Inputs!$B$16*(1/(1+Inputs!$B$6))+(1-I15)*(1-D15)*(1/(1+Inputs!$B$6))*J16 -> 458.67719 | K15: =MIN(D15*(1+Inputs!$B$33),1) -> 0.075 | L15: =F15-E15+C15*Inputs!$B$16*(1/(1+Inputs!$B$6))+(1-C15)*(1-K15)*(1/(1+Inputs!$B$6))*L16 -> 22.4554 | M15: =MAX(D15*(1+Inputs!$B$34),D15-Inputs!$B$35) -> 0.025 | N15: =F15-E15+C15*Inputs!$B$16*(1/(1+Inputs!$B$6))+(1-C15)*(1-M15)*(1/(1+Inputs!$B$6))*N16 -> 183.09517 | O15: =F15*(1+Inputs!$B$36) -> 86.11503 | P15: =O15-E15+C15*Inputs!$B$16*(1/(1+Inputs!$B$6))+(1-C15)*(1-D15)*(1/(1+Inputs!$B$6))*P16 -> 161.06311 | Q15: =C15*Inputs!$B$16*(1/(1+Inputs!$B$6))+(1-C15)*(1-D15)*(1/(1+Inputs!$B$6))*Q16 -> 2439.0358 | R15: =F15+(1-C15)*(1-D15)*(1/(1+Inputs!$B$6))*R16 -> 670.8432 | S15: =E15+(1-C15)*(1-D15)*(1/(1+Inputs!$B$6))*S16 -> 3015.9002 | T15: =G15*H15 -> 588560.78 | U15: =G15*MAX(J15-H15,0) -> 2283996 | V15: =G15*MAX(L15-H15,N15-H15,0) -> 558108.97 | W15: =G15*MAX(P15-H15,0) -> 420128.84 | X15: =G15*Inputs!$B$16 -> 1.2525396e+09 | Y15: =G15*Q15 -> 15274945 | Z15: =G15*MAX(S15-Q15-R15,0) -> 0 | AA15: =G15*R15 -> 4201288.4 | AB15: =H15-(Q15+R15-S15) -> -3.9790393e-13
A16: 10 | B16: =Inputs!$B$14+A16 -> 50 | C16: =MIN(Inputs!$B$21*(1-EXP(-(Inputs!$B$8+Inputs!$B$9*Inputs!$B$10^B16))),1) -> 0.0011519015 | D16: =Inputs!$B$20 -> 0.05 | E16: =Inputs!$B$17 -> 400 | F16: =Inputs!$B$18*(1+Inputs!$B$19)^A16 -> 80.634983 | G16: =G15*(1-C15)*(1-D15) -> 5943.3213 | H16: =F16-E16+C16*Inputs!$B$16*(1/(1+Inputs!$B$6))+(1-C16)*(1-D16)*(1/(1+Inputs!$B$6))*H17 -> 230.06916 | I16: =MIN(C16*(1+Inputs!$B$31),1) -> 0.0013246867 | J16: =F16-E16+I16*Inputs!$B$16*(1/(1+Inputs!$B$6))+(1-I16)*(1-D16)*(1/(1+Inputs!$B$6))*J17 -> 592.82233 | K16: =MIN(D16*(1+Inputs!$B$33),1) -> 0.075 | L16: =F16-E16+C16*Inputs!$B$16*(1/(1+Inputs!$B$6))+(1-C16)*(1-K16)*(1/(1+Inputs!$B$6))*L17 -> 156.56135 | M16: =MAX(D16*(1+Inputs!$B$34),D16-Inputs!$B$35) -> 0.025 | N16: =F16-E16+C16*Inputs!$B$16*(1/(1+Inputs!$B$6))+(1-C16)*(1-M16)*(1/(1+Inputs!$B$6))*N17 -> 318.41228 | O16: =F16*(1+Inputs!$B$36) -> 88.698481 | P16: =O16-E16+C16*Inputs!$B$16*(1/(1+Inputs!$B$6))+(1-C16)*(1-D16)*(1/(1+Inputs!$B$6))*P17 -> 294.38227 | Q16: =C16*Inputs!$B$16*(1/(1+Inputs!$B$6))+(1-C16)*(1-D16)*(1/(1+Inputs!$B$6))*Q17 -> 2426.1033 | R16: =F16+(1-C16)*(1-D16)*(1/(1+Inputs!$B$6))*R17 -> 643.13107 | S16: =E16+(1-C16)*(1-D16)*(1/(1+Inputs!$B$6))*S17 -> 2839.1652 | T16: =G16*H16 -> 1367375 | U16: =G16*MAX(J16-H16,0) -> 2155958.6 | V16: =G16*MAX(L16-H16,N16-H16,0) -> 525051.54 | W16: =G16*MAX(P16-H16,0) -> 382233.45 | X16: =G16*Inputs!$B$16 -> 1.1886643e+09 | Y16: =G16*Q16 -> 14419111 | Z16: =G16*MAX(S16-Q16-R16,0) -> 0 | AA16: =G16*R16 -> 3822334.5 | AB16: =H16-(Q16+R16-S16) -> 0
A17: 11 | B17: =Inputs!$B$14+A17 -> 51 | C17: =MIN(Inputs!$B$21*(1-EXP(-(Inputs!$B$8+Inputs!$B$9*Inputs!$B$10^B17))),1) -> 0.0012673997 | D17: =Inputs!$B$20 -> 0.05 | E17: =Inputs!$B$17 -> 400 | F17: =Inputs!$B$18*(1+Inputs!$B$19)^A17 -> 83.054032 | G17: =G16*(1-C16)*(1-D16) -> 5639.6514 | H17: =F17-E17+C17*Inputs!$B$16*(1/(1+Inputs!$B$6))+(1-C17)*(1-D17)*(1/(1+Inputs!$B$6))*H18 -> 353.60406 | I17: =MIN(C17*(1+Inputs!$B$31),1) -> 0.0014575097 | J17: =F17-E17+I17*Inputs!$B$16*(1/(1+Inputs!$B$6))+(1-I17)*(1-D17)*(1/(1+Inputs!$B$6))*J18 -> 711.06365 | K17: =MIN(D17*(1+Inputs!$B$33),1) -> 0.075 | L17: =F17-E17+C17*Inputs!$B$16*(1/(1+Inputs!$B$6))+(1-C17)*(1-K17)*(1/(1+Inputs!$B$6))*L18 -> 281.21458 | M17: =MAX(D17*(1+Inputs!$B$34),D17-Inputs!$B$35) -> 0.025 | N17: =F17-E17+C17*Inputs!$B$16*(1/(1+Inputs!$B$6))+(1-C17)*(1-M17)*(1/(1+Inputs!$B$6))*N18 -> 437.97149 | O17: =F17*(1+Inputs!$B$36) -> 91.359435 | P17: =O17-E17+C17*Inputs!$B$16*(1/(1+Inputs!$B$6))+(1-C17)*(1-D17)*(1/(1+Inputs!$B$6))*P18 -> 414.66081 | Q17: =C17*Inputs!$B$16*(1/(1+Inputs!$B$6))+(1-C17)*(1-D17)*(1/(1+Inputs!$B$6))*Q18 -> 2390.6549 | R17: =F17+(1-C17)*(1-D17)*(1/(1+Inputs!$B$6))*R18 -> 610.56749 | S17: =E17+(1-C17)*(1-D17)*(1/(1+Inputs!$B$6))*S18 -> 2647.6184 | T17: =G17*H17 -> 1994203.6 | U17: =G17*MAX(J17-H17,0) -> 2015947.5 | V17: =G17*MAX(L17-H17,N17-H17,0) -> 475802.92 | W17: =G17*MAX(P17-H17,0) -> 344338.78 | X17: =G17*Inputs!$B$16 -> 1.1279303e+09 | Y17: =G17*Q17 -> 13482460 | Z17: =G17*MAX(S17-Q17-R17,0) -> 0 | AA17: =G17*R17 -> 3443387.8 | AB17: =H17-(Q17+R17-S17) -> 0
A18: 12 | B18: =Inputs!$B$14+A18 -> 52 | C18: =MIN(Inputs!$B$21*(1-EXP(-(Inputs!$B$8+Inputs!$B$9*Inputs!$B$10^B18))),1) -> 0.0013972038 | D18: =Inputs!$B$20 -> 0.05 | E18: =Inputs!$B$17 -> 400 | F18: =Inputs!$B$18*(1+Inputs!$B$19)^A18 -> 85.545653 | G18: =G17*(1-C17)*(1-D17) -> 5350.8785 | H18: =F18-E18+C18*Inputs!$B$16*(1/(1+Inputs!$B$6))+(1-C18)*(1-D18)*(1/(1+Inputs!$B$6))*H19 -> 460.78039 | I18: =MIN(C18*(1+Inputs!$B$31),1) -> 0.0016067844 | J18: =F18-E18+I18*Inputs!$B$16*(1/(1+Inputs!$B$6))+(1-I18)*(1-D18)*(1/(1+Inputs!$B$6))*J19 -> 808.91369 | K18: =MIN(D18*(1+Inputs!$B$33),1) -> 0.075 | L18: =F18-E18+C18*Inputs!$B$16*(1/(1+Inputs!$B$6))+(1-C18)*(1-K18)*(1/(1+Inputs!$B$6))*L19 -> 392.52496 | M18: =MAX(D18*(1+Inputs!$B$34),D18-Inputs!$B$35) -> 0.025 | N18: =F18-E18+C18*Inputs!$B$16*(1/(1+Inputs!$B$6))+(1-C18)*(1-M18)*(1/(1+Inputs!$B$6))*N19 -> 538.20523 | O18: =F18*(1+Inputs!$B$36) -> 94.100219 | P18: =O18-E18+C18*Inputs!$B$16*(1/(1+Inputs!$B$6))+(1-C18)*(1-D18)*(1/(1+Inputs!$B$6))*P19 -> 518.04653 | Q18: =C18*Inputs!$B$16*(1/(1+Inputs!$B$6))+(1-C18)*(1-D18)*(1/(1+Inputs!$B$6))*Q19 -> 2328.1029 | R18: =F18+(1-C18)*(1-D18)*(1/(1+Inputs!$B$6))*R19 -> 572.66143 | S18: =E18+(1-C18)*(1-D18)*(1/(1+Inputs!$B$6))*S19 -> 2439.9839 | T18: =G18*H18 -> 2465579.9 | U18: =G18*MAX(J18-H18,0) -> 1862819 | V18: =G18*MAX(L18-H18,N18-H18,0) -> 414290.93 | W18: =G18*MAX(P18-H18,0) -> 306424.18 | X18: =G18*Inputs!$B$16 -> 1.0701757e+09 | Y18: =G18*Q18 -> 12457396 | Z18: =G18*MAX(S18-Q18-R18,0) -> 0 | AA18: =G18*R18 -> 3064241.8 | AB18: =H18-(Q18+R18-S18) -> 0
... A25: 19 | B25: =Inputs!$B$14+A25 -> 59 | C25: =MIN(Inputs!$B$21*(1-EXP(-(Inputs!$B$8+Inputs!$B$9*Inputs!$B$10^B25))),1) -> 0.0028862256 | D25: =Inputs!$B$20 -> 0.05 | E25: =Inputs!$B$17 -> 400 | F25: =Inputs!$B$18*(1+Inputs!$B$19)^A25 -> 105.21036 | G25: =G24*(1-C24)*(1-D24) -> 3686.3385 | H25: =F25-E25+C25*Inputs!$B$16*(1/(1+Inputs!$B$6))+(1-C25)*(1-D25)*(1/(1+Inputs!$B$6))*H26 -> 265.64253 | I25: =MIN(C25*(1+Inputs!$B$31),1) -> 0.0033191595 | J25: =F25-E25+I25*Inputs!$B$16*(1/(1+Inputs!$B$6))+(1-I25)*(1-D25)*(1/(1+Inputs!$B$6))*J26 -> 349.70735 | K25: =MIN(D25*(1+Inputs!$B$33),1) -> 0.075 | L25: =F25-E25+C25*Inputs!$B$16*(1/(1+Inputs!$B$6))+(1-C25)*(1-K25)*(1/(1+Inputs!$B$6))*L26 -> 265.64253 | M25: =MAX(D25*(1+Inputs!$B$34),D25-Inputs!$B$35) -> 0.025 | N25: =F25-E25+C25*Inputs!$B$16*(1/(1+Inputs!$B$6))+(1-C25)*(1-M25)*(1/(1+Inputs!$B$6))*N26 -> 265.64253 | O25: =F25*(1+Inputs!$B$36) -> 115.7314 | P25: =O25-E25+C25*Inputs!$B$16*(1/(1+Inputs!$B$6))+(1-C25)*(1-D25)*(1/(1+Inputs!$B$6))*P26 -> 276.16356 | Q25: =C25*Inputs!$B$16*(1/(1+Inputs!$B$6))+(1-C25)*(1-D25)*(1/(1+Inputs!$B$6))*Q26 -> 560.43216 | R25: =F25+(1-C25)*(1-D25)*(1/(1+Inputs!$B$6))*R26 -> 105.21036 | S25: =E25+(1-C25)*(1-D25)*(1/(1+Inputs!$B$6))*S26 -> 400 | T25: =G25*H25 -> 979248.26 | U25: =G25*MAX(J25-H25,0) -> 309891.4 | V25: =G25*MAX(L25-H25,N25-H25,0) -> 0 | W25: =G25*MAX(P25-H25,0) -> 38784.101 | X25: =G25*Inputs!$B$16 -> 7.3726769e+08 | Y25: =G25*Q25 -> 2065942.6 | Z25: =G25*MAX(S25-Q25-R25,0) -> 0 | AA25: =G25*R25 -> 387841.01 | AB25: =H25-(Q25+R25-S25) -> 0
A26: end | H26: 0 | J26: 0 | L26: 0 | N26: 0 | P26: 0 | Q26: 0 | R26: 0 | S26: 0

Sheet Annuity
A1: Immediate annuity group: per-policy BEL on each basis, capital and exposures
A2: Per-policy BEL(t) = expense + (1 − q) × annuity × v + (1 − q) × v × BEL(t+1).
A3: Capital = in-force × (stressed BEL − best-estimate BEL), floored at 0.
A5: t | B5: Age | C5: q (best est.) | D5: Annuity per survivor | E5: Expense per policy | F5: In-force at start of year | G5: BEL per policy: best estimate | H5: q (longevity stress) | I5: BEL per policy: longevity stress | J5: Expense (stressed) | K5: BEL per policy: expense stress | L5: PV future annuity payments per policy | M5: PV future expenses per policy | N5: BEL total (group) | O5: Capital: longevity | P5: Capital: expense | Q5: Exposure: PV future annuity payments | R5: Exposure: PV future expenses
A6: 0 | B6: =Inputs!$B$25+A6 -> 65 | C6: =MIN(Inputs!$B$28*(1-EXP(-(Inputs!$B$8+Inputs!$B$9*Inputs!$B$10^B6))),1) -> 0.0041918827 | D6: =Inputs!$B$26 -> 12000 | E6: =Inputs!$B$27*(1+Inputs!$B$19)^A6 -> 90 | F6: =Inputs!$B$24 -> 300 | G6: =E6+(1-C6)*D6*(1/(1+Inputs!$B$6))+(1-C6)*(1/(1+Inputs!$B$6))*G7 -> 203497.22 | H6: =MIN(MAX(C6*(1+Inputs!$B$32),0),1) -> 0.0033535061 | I6: =E6+(1-H6)*D6*(1/(1+Inputs!$B$6))+(1-H6)*(1/(1+Inputs!$B$6))*I7 -> 213617.71 | J6: =E6*(1+Inputs!$B$36) -> 99 | K6: =J6+(1-C6)*D6*(1/(1+Inputs!$B$6))+(1-C6)*(1/(1+Inputs!$B$6))*K7 -> 203730.99 | L6: =(1-C6)*D6*(1/(1+Inputs!$B$6))+(1-C6)*(1/(1+Inputs!$B$6))*L7 -> 201159.51 | M6: =E6+(1-C6)*(1/(1+Inputs!$B$6))*M7 -> 2337.7056 | N6: =F6*G6 -> 61049166 | O6: =F6*MAX(I6-G6,0) -> 3036146.4 | P6: =F6*MAX(K6-G6,0) -> 70131.167 | Q6: =F6*L6 -> 60347854 | R6: =F6*M6 -> 701311.67
A7: 1 | B7: =Inputs!$B$25+A7 -> 66 | C7: =MIN(Inputs!$B$28*(1-EXP(-(Inputs!$B$8+Inputs!$B$9*Inputs!$B$10^B7))),1) -> 0.0046897089 | D7: =Inputs!$B$26 -> 12000 | E7: =Inputs!$B$27*(1+Inputs!$B$19)^A7 -> 92.7 | F7: =F6*(1-C6) -> 298.74244 | G7: =E7+(1-C7)*D7*(1/(1+Inputs!$B$6))+(1-C7)*(1/(1+Inputs!$B$6))*G8 -> 198391.37 | H7: =MIN(MAX(C7*(1+Inputs!$B$32),0),1) -> 0.0037517671 | I7: =E7+(1-H7)*D7*(1/(1+Inputs!$B$6))+(1-H7)*(1/(1+Inputs!$B$6))*I8 -> 208673.57 | J7: =E7*(1+Inputs!$B$36) -> 101.97 | K7: =J7+(1-C7)*D7*(1/(1+Inputs!$B$6))+(1-C7)*(1/(1+Inputs!$B$6))*K8 -> 198623.86 | L7: =(1-C7)*D7*(1/(1+Inputs!$B$6))+(1-C7)*(1/(1+Inputs!$B$6))*L8 -> 196066.49 | M7: =E7+(1-C7)*(1/(1+Inputs!$B$6))*M8 -> 2324.8824 | N7: =F7*G7 -> 59267921 | O7: =F7*MAX(I7-G7,0) -> 3071728.5 | P7: =F7*MAX(K7-G7,0) -> 69454.102 | Q7: =F7*L7 -> 58573380 | R7: =F7*M7 -> 694541.02
A8: 2 | B8: =Inputs!$B$25+A8 -> 67 | C8: =MIN(Inputs!$B$28*(1-EXP(-(Inputs!$B$8+Inputs!$B$9*Inputs!$B$10^B8))),1) -> 0.005248869 | D8: =Inputs!$B$26 -> 12000 | E8: =Inputs!$B$27*(1+Inputs!$B$19)^A8 -> 95.481 | F8: =F7*(1-C7) -> 297.34142 | G8: =E8+(1-C8)*D8*(1/(1+Inputs!$B$6))+(1-C8)*(1/(1+Inputs!$B$6))*G9 -> 193210.01 | H8: =MIN(MAX(C8*(1+Inputs!$B$32),0),1) -> 0.0041990952 | I8: =E8+(1-H8)*D8*(1/(1+Inputs!$B$6))+(1-H8)*(1/(1+Inputs!$B$6))*I9 -> 203647.35 | J8: =E8*(1+Inputs!$B$36) -> 105.0291 | K8: =J8+(1-C8)*D8*(1/(1+Inputs!$B$6))+(1-C8)*(1/(1+Inputs!$B$6))*K9 -> 193441 | L8: =(1-C8)*D8*(1/(1+Inputs!$B$6))+(1-C8)*(1/(1+Inputs!$B$6))*L9 -> 190900.03 | M8: =E8+(1-C8)*(1/(1+Inputs!$B$6))*M9 -> 2309.981 | N8: =F8*G8 -> 57449338 | O8: =F8*MAX(I8-G8,0) -> 3103455.3 | P8: =F8*MAX(K8-G8,0) -> 68685.302 | Q8: =F8*L8 -> 56762485 | R8: =F8*M8 -> 686853.02
A9: 3 | B9: =Inputs!$B$25+A9 -> 68 | C9: =MIN(Inputs!$B$28*(1-EXP(-(Inputs!$B$8+Inputs!$B$9*Inputs!$B$10^B9))),1) -> 0.0058768641 | D9: =Inputs!$B$26 -> 12000 | E9: =Inputs!$B$27*(1+Inputs!$B$19)^A9 -> 98.34543 | F9: =F8*(1-C8) -> 295.78071 | G9: =E9+(1-C9)*D9*(1/(1+Inputs!$B$6))+(1-C9)*(1/(1+Inputs!$B$6))*G10 -> 187957.51 | H9: =MIN(MAX(C9*(1+Inputs!$B$32),0),1) -> 0.0047014913 | I9: =E9+(1-H9)*D9*(1/(1+Inputs!$B$6))+(1-H9)*(1/(1+Inputs!$B$6))*I10 -> 198542.52 | J9: =E9*(1+Inputs!$B$36) -> 108.17997 | K9: =J9+(1-C9)*D9*(1/(1+Inputs!$B$6))+(1-C9)*(1/(1+Inputs!$B$6))*K10 -> 188186.81 | L9: =(1-C9)*D9*(1/(1+Inputs!$B$6))+(1-C9)*(1/(1+Inputs!$B$6))*L10 -> 185664.54 | M9: =E9+(1-C9)*(1/(1+Inputs!$B$6))*M10 -> 2292.9705 | N9: =F9*G9 -> 55594207 | O9: =F9*MAX(I9-G9,0) -> 3130840 | P9: =F9*MAX(K9-G9,0) -> 67821.644 | Q9: =F9*L9 -> 54915991 | R9: =F9*M9 -> 678216.44
A10: 4 | B10: =Inputs!$B$25+A10 -> 69 | C10: =MIN(Inputs!$B$28*(1-EXP(-(Inputs!$B$8+Inputs!$B$9*Inputs!$B$10^B10))),1) -> 0.0065820986 | D10: =Inputs!$B$26 -> 12000 | E10: =Inputs!$B$27*(1+Inputs!$B$19)^A10 -> 101.29579 | F10: =F9*(1-C9) -> 294.04245 | G10: =E10+(1-C10)*D10*(1/(1+Inputs!$B$6))+(1-C10)*(1/(1+Inputs!$B$6))*G11 -> 182638.81 | H10: =MIN(MAX(C10*(1+Inputs!$B$32),0),1) -> 0.0052656789 | I10: =E10+(1-H10)*D10*(1/(1+Inputs!$B$6))+(1-H10)*(1/(1+Inputs!$B$6))*I11 -> 193363.01 | J10: =E10*(1+Inputs!$B$36) -> 111.42537 | K10: =J10+(1-C10)*D10*(1/(1+Inputs!$B$6))+(1-C10)*(1/(1+Inputs!$B$6))*K11 -> 182866.19 | L10: =(1-C10)*D10*(1/(1+Inputs!$B$6))+(1-C10)*(1/(1+Inputs!$B$6))*L11 -> 180364.98 | M10: =E10+(1-C10)*(1/(1+Inputs!$B$6))*M11 -> 2273.8268 | N10: =F10*G10 -> 53703562 | O10: =F10*MAX(I10-G10,0) -> 3153370.2 | P10: =F10*MAX(K10-G10,0) -> 66860.159 | Q10: =F10*L10 -> 53034961 | R10: =F10*M10 -> 668601.59
A11: 5 | B11: =Inputs!$B$25+A11 -> 70 | C11: =MIN(Inputs!$B$28*(1-EXP(-(Inputs!$B$8+Inputs!$B$9*Inputs!$B$10^B11))),1) -> 0.0073739844 | D11: =Inputs!$B$26 -> 12000 | E11: =Inputs!$B$27*(1+Inputs!$B$19)^A11 -> 104.33467 | F11: =F10*(1-C10) -> 292.10703 | G11: =E11+(1-C11)*D11*(1/(1+Inputs!$B$6))+(1-C11)*(1/(1+Inputs!$B$6))*G12 -> 177259.36 | H11: =MIN(MAX(C11*(1+Inputs!$B$32),0),1) -> 0.0058991875 | I11: =E11+(1-H11)*D11*(1/(1+Inputs!$B$6))+(1-H11)*(1/(1+Inputs!$B$6))*I12 -> 188113.3 | J11: =E11*(1+Inputs!$B$36) -> 114.76813 | K11: =J11+(1-C11)*D11*(1/(1+Inputs!$B$6))+(1-C11)*(1/(1+Inputs!$B$6))*K12 -> 177484.61 | L11: =(1-C11)*D11*(1/(1+Inputs!$B$6))+(1-C11)*(1/(1+Inputs!$B$6))*L12 -> 175006.83 | M11: =E11+(1-C11)*(1/(1+Inputs!$B$6))*M12 -> 2252.5333 | N11: =F11*G11 -> 51778706 | O11: =F11*MAX(I11-G11,0) -> 3170510.8 | P11: =F11*MAX(K11-G11,0) -> 65798.082 | Q11: =F11*L11 -> 51120725 | R11: =F11*M11 -> 657980.82
A12: 6 | B12: =Inputs!$B$25+A12 -> 71 | C12: =MIN(Inputs!$B$28*(1-EXP(-(Inputs!$B$8+Inputs!$B$9*Inputs!$B$10^B12))),1) -> 0.0082630571 | D12: =Inputs!$B$26 -> 12000 | E12: =Inputs!$B$27*(1+Inputs!$B$19)^A12 -> 107.46471 | F12: =F11*(1-C11) -> 289.95304 | G12: =E12+(1-C12)*D12*(1/(1+Inputs!$B$6))+(1-C12)*(1/(1+Inputs!$B$6))*G13 -> 171825.2 | H12: =MIN(MAX(C12*(1+Inputs!$B$32),0),1) -> 0.0066104457 | I12: =E12+(1-H12)*D12*(1/(1+Inputs!$B$6))+(1-H12)*(1/(1+Inputs!$B$6))*I13 -> 182798.38 | J12: =E12*(1+Inputs!$B$36) -> 118.21118 | K12: =J12+(1-C12)*D12*(1/(1+Inputs!$B$6))+(1-C12)*(1/(1+Inputs!$B$6))*K13 -> 172048.11 | L12: =(1-C12)*D12*(1/(1+Inputs!$B$6))+(1-C12)*(1/(1+Inputs!$B$6))*L13 -> 169596.12 | M12: =E12+(1-C12)*(1/(1+Inputs!$B$6))*M13 -> 2229.0818 | N12: =F12*G12 -> 49821240 | O12: =F12*MAX(I12-G12,0) -> 3181707.2 | P12: =F12*MAX(K12-G12,0) -> 64632.905 | Q12: =F12*L12 -> 49174911 | R12: =F12*M12 -> 646329.05
A13: 7 | B13: =Inputs!$B$25+A13 -> 72 | C13: =MIN(Inputs!$B$28*(1-EXP(-(Inputs!$B$8+Inputs!$B$9*Inputs!$B$10^B13))),1) -> 0.0092611044 | D13: =Inputs!$B$26 -> 12000 | E13: =Inputs!$B$27*(1+Inputs!$B$19)^A13 -> 110.68865 | F13: =F12*(1-C12) -> 287.55714 | G13: =E13+(1-C13)*D13*(1/(1+Inputs!$B$6))+(1-C13)*(1/(1+Inputs!$B$6))*G14 -> 166342.93 | H13: =MIN(MAX(C13*(1+Inputs!$B$32),0),1) -> 0.0074088835 | I13: =E13+(1-H13)*D13*(1/(1+Inputs!$B$6))+(1-H13)*(1/(1+Inputs!$B$6))*I14 -> 177423.82 | J13: =E13*(1+Inputs!$B$36) -> 121.75751 | K13: =J13+(1-C13)*D13*(1/(1+Inputs!$B$6))+(1-C13)*(1/(1+Inputs!$B$6))*K14 -> 166563.27 | L13: =(1-C13)*D13*(1/(1+Inputs!$B$6))+(1-C13)*(1/(1+Inputs!$B$6))*L14 -> 164139.45 | M13: =E13+(1-C13)*(1/(1+Inputs!$B$6))*M14 -> 2203.473 | N13: =F13*G13 -> 47833097 | O13: =F13*MAX(I13-G13,0) -> 3186390.4 | P13: =F13*MAX(K13-G13,0) -> 63362.441 | Q13: =F13*L13 -> 47199472 | R13: =F13*M13 -> 633624.41
A14: 8 | B14: =Inputs!$B$25+A14 -> 73 | C14: =MIN(Inputs!$B$28*(1-EXP(-(Inputs!$B$8+Inputs!$B$9*Inputs!$B$10^B14))),1) -> 0.010381307 | D14: =Inputs!$B$26 -> 12000 | E14: =Inputs!$B$27*(1+Inputs!$B$19)^A14 -> 114.00931 | F14: =F13*(1-C13) -> 284.89405 | G14: =E14+(1-C14)*D14*(1/(1+Inputs!$B$6))+(1-C14)*(1/(1+Inputs!$B$6))*G15 -> 160819.71 | H14: =MIN(MAX(C14*(1+Inputs!$B$32),0),1) -> 0.0083050453 | I14: =E14+(1-H14)*D14*(1/(1+Inputs!$B$6))+(1-H14)*(1/(1+Inputs!$B$6))*I15 -> 171995.73 | J14: =E14*(1+Inputs!$B$36) -> 125.41024 | K14: =J14+(1-C14)*D14*(1/(1+Inputs!$B$6))+(1-C14)*(1/(1+Inputs!$B$6))*K15 -> 161037.28 | L14: =(1-C14)*D14*(1/(1+Inputs!$B$6))+(1-C14)*(1/(1+Inputs!$B$6))*L15 -> 158643.99 | M14: =E14+(1-C14)*(1/(1+Inputs!$B$6))*M15 -> 2175.7175 | N14: =F14*G14 -> 45816577 | O14: =F14*MAX(I14-G14,0) -> 3183982.4 | P14: =F14*MAX(K14-G14,0) -> 61984.895 | Q14: =F14*L14 -> 45196728 | R14: =F14*M14 -> 619848.95
A15: 9 | B15: =Inputs!$B$25+A15 -> 74 | C15: =MIN(Inputs!$B$28*(1-EXP(-(Inputs!$B$8+Inputs!$B$9*Inputs!$B$10^B15))),1) -> 0.011638392 | D15: =Inputs!$B$26 -> 12000 | E15: =Inputs!$B$27*(1+Inputs!$B$19)^A15 -> 117.42959 | F15: =F14*(1-C14) -> 281.93647 | G15: =E15+(1-C15)*D15*(1/(1+Inputs!$B$6))+(1-C15)*(1/(1+Inputs!$B$6))*G16 -> 155263.28 | H15: =MIN(MAX(C15*(1+Inputs!$B$32),0),1) -> 0.0093107134 | I15: =E15+(1-H15)*D15*(1/(1+Inputs!$B$6))+(1-H15)*(1/(1+Inputs!$B$6))*I16 -> 166520.79 | J15: =E15*(1+Inputs!$B$36) -> 129.17255 | K15: =J15+(1-C15)*D15*(1/(1+Inputs!$B$6))+(1-C15)*(1/(1+Inputs!$B$6))*K16 -> 155477.86 | L15: =(1-C15)*D15*(1/(1+Inputs!$B$6))+(1-C15)*(1/(1+Inputs!$B$6))*L16 -> 153117.44 | M15: =E15+(1-C15)*(1/(1+Inputs!$B$6))*M16 -> 2145.836 | N15: =F15*G15 -> 43774381 | O15: =F15*MAX(I15-G15,0) -> 3173904.3 | P15: =F15*MAX(K15-G15,0) -> 60498.943 | Q15: =F15*L15 -> 43169392 | R15: =F15*M15 -> 604989.43
A16: 10 | B16: =Inputs!$B$25+A16 -> 75 | C16: =MIN(Inputs!$B$28*(1-EXP(-(Inputs!$B$8+Inputs!$B$9*Inputs!$B$10^B16))),1) -> 0.013048805 | D16: =Inputs!$B$26 -> 12000 | E16: =Inputs!$B$27*(1+Inputs!$B$19)^A16 -> 120.95247 | F16: =F15*(1-C15) -> 278.65519 | G16: =E16+(1-C16)*D16*(1/(1+Inputs!$B$6))+(1-C16)*(1/(1+Inputs!$B$6))*G17 -> 149681.94 | H16: =MIN(MAX(C16*(1+Inputs!$B$32),0),1) -> 0.010439044 | I16: =E16+(1-H16)*D16*(1/(1+Inputs!$B$6))+(1-H16)*(1/(1+Inputs!$B$6))*I17 -> 161006.28 | J16: =E16*(1+Inputs!$B$36) -> 133.04772 | K16: =J16+(1-C16)*D16*(1/(1+Inputs!$B$6))+(1-C16)*(1/(1+Inputs!$B$6))*K17 -> 149893.33 | L16: =(1-C16)*D16*(1/(1+Inputs!$B$6))+(1-C16)*(1/(1+Inputs!$B$6))*L17 -> 147568.08 | M16: =E16+(1-C16)*(1/(1+Inputs!$B$6))*M17 -> 2113.8605 | N16: =F16*G16 -> 41709650 | O16: =F16*MAX(I16-G16,0) -> 3155584.7 | P16: =F16*MAX(K16-G16,0) -> 58903.82 | Q16: =F16*L16 -> 41120611 | R16: =F16*M16 -> 589038.2
A17: 11 | B17: =Inputs!$B$25+A17 -> 76 | C17: =MIN(Inputs!$B$28*(1-EXP(-(Inputs!$B$8+Inputs!$B$9*Inputs!$B$10^B17))),1) -> 0.014630894 | D17: =Inputs!$B$26 -> 12000 | E17: =Inputs!$B$27*(1+Inputs!$B$19)^A17 -> 124.58105 | F17: =F16*(1-C16) -> 275.01907 | G17: =E17+(1-C17)*D17*(1/(1+Inputs!$B$6))+(1-C17)*(1/(1+Inputs!$B$6))*G18 -> 144084.54 | H17: =MIN(MAX(C17*(1+Inputs!$B$32),0),1) -> 0.011704715 | I17: =E17+(1-H17)*D17*(1/(1+Inputs!$B$6))+(1-H17)*(1/(1+Inputs!$B$6))*I18 -> 155460.01 | J17: =E17*(1+Inputs!$B$36) -> 137.03915 | K17: =J17+(1-C17)*D17*(1/(1+Inputs!$B$6))+(1-C17)*(1/(1+Inputs!$B$6))*K18 -> 144292.52 | L17: =(1-C17)*D17*(1/(1+Inputs!$B$6))+(1-C17)*(1/(1+Inputs!$B$6))*L18 -> 142004.7 | M17: =E17+(1-C17)*(1/(1+Inputs!$B$6))*M18 -> 2079.8346 | N17: =F17*G17 -> 39625995 | O17: =F17*MAX(I17-G17,0) -> 3128471.4 | P17: =F17*MAX(K17-G17,0) -> 57199.419 | Q17: =F17*L17 -> 39054001 | R17: =F17*M17 -> 571994.19
A18: 12 | B18: =Inputs!$B$25+A18 -> 77 | C18: =MIN(Inputs!$B$28*(1-EXP(-(Inputs!$B$8+Inputs!$B$9*Inputs!$B$10^B18))),1) -> 0.016405109 | D18: =Inputs!$B$26 -> 12000 | E18: =Inputs!$B$27*(1+Inputs!$B$19)^A18 -> 128.31848 | F18: =F17*(1-C17) -> 270.99529 | G18: =E18+(1-C18)*D18*(1/(1+Inputs!$B$6))+(1-C18)*(1/(1+Inputs!$B$6))*G19 -> 138480.42 | H18: =MIN(MAX(C18*(1+Inputs!$B$32),0),1) -> 0.013124087 | I18: =E18+(1-H18)*D18*(1/(1+Inputs!$B$6))+(1-H18)*(1/(1+Inputs!$B$6))*I19 -> 149890.37 | J18: =E18*(1+Inputs!$B$36) -> 141.15033 | K18: =J18+(1-C18)*D18*(1/(1+Inputs!$B$6))+(1-C18)*(1/(1+Inputs!$B$6))*K19 -> 138684.8 | L18: =(1-C18)*D18*(1/(1+Inputs!$B$6))+(1-C18)*(1/(1+Inputs!$B$6))*L19 -> 136436.6 | M18: =E18+(1-C18)*(1/(1+Inputs!$B$6))*M19 -> 2043.814 | N18: =F18*G18 -> 37527541 | O18: =F18*MAX(I18-G18,0) -> 3092043.5 | P18: =F18*MAX(K18-G18,0) -> 55386.398 | Q18: =F18*L18 -> 36973677 | R18: =F18*M18 -> 553863.98
... A50: 44 | B50: =Inputs!$B$25+A50 -> 109 | C50: =MIN(Inputs!$B$28*(1-EXP(-(Inputs!$B$8+Inputs!$B$9*Inputs!$B$10^B50))),1) -> 0.45187531 | D50: =Inputs!$B$26 -> 12000 | E50: =Inputs!$B$27*(1+Inputs!$B$19)^A50 -> 330.4307 | F50: =F49*(1-C49) -> 1.6172029 | G50: =E50+(1-C50)*D50*(1/(1+Inputs!$B$6))+(1-C50)*(1/(1+Inputs!$B$6))*G51 -> 6716.3495 | H50: =MIN(MAX(C50*(1+Inputs!$B$32),0),1) -> 0.36150024 | I50: =E50+(1-H50)*D50*(1/(1+Inputs!$B$6))+(1-H50)*(1/(1+Inputs!$B$6))*I51 -> 7769.2628 | J50: =E50*(1+Inputs!$B$36) -> 363.47378 | K50: =J50+(1-C50)*D50*(1/(1+Inputs!$B$6))+(1-C50)*(1/(1+Inputs!$B$6))*K51 -> 6749.3925 | L50: =(1-C50)*D50*(1/(1+Inputs!$B$6))+(1-C50)*(1/(1+Inputs!$B$6))*L51 -> 6385.9188 | M50: =E50+(1-C50)*(1/(1+Inputs!$B$6))*M51 -> 330.4307 | N50: =F50*G50 -> 10861.7 | O50: =F50*MAX(I50-G50,0) -> 1702.7745 | P50: =F50*MAX(K50-G50,0) -> 53.437348 | Q50: =F50*L50 -> 10327.326 | R50: =F50*M50 -> 534.37348
A51: end | G51: 0 | I51: 0 | K51: 0 | L51: 0 | M51: 0

Sheet Capital
A1: Capital each year: by risk, diversified, standalone by group, and Euler allocation to groups
A2: Diversified capital = √(Σi Σj ρij Ci Cj) across both groups. Standalone = each group on its own. Euler: risk i's share = Ci × (Σj ρij Cj) ÷ total.
A5: t | B5: Mortality (term) | C5: Longevity (annuity) | D5: Lapse (term) | E5: Expense (term) | F5: Expense (annuity) | G5: Expense (total) | H5: Σj ρ(mort,j)·Cj | I5: Σj ρ(long,j)·Cj | J5: Σj ρ(lapse,j)·Cj | K5: Σj ρ(exp,j)·Cj | L5: Diversified capital (both groups) | M5: Standalone capital: term | N5: Standalone capital: annuity | O5: Sum of standalone | P5: Diversification benefit | Q5: Euler share: mortality | R5: Euler share: longevity | S5: Euler share: lapse | T5: Euler share: expense | U5: Allocated capital: term | V5: Allocated capital: annuity | W5: Check: allocations − total | X5: Proportional allocation: term | Y5: Proportional allocation: annuity
A6: 0 | B6: =Term!U6 -> 3055572.5 | C6: =Annuity!O6 -> 3036146.4 | D6: =Term!V6 -> 661794.1 | E6: =Term!W6 -> 764711.77 | F6: =Annuity!P6 -> 70131.167 | G6: =E6+F6 -> 834842.94 | H6: =Inputs!$B$40*B6+Inputs!$C$40*C6+Inputs!$D$40*D6+Inputs!$E$40*G6 -> 2505246.6 | I6: =Inputs!$B$41*B6+Inputs!$C$41*C6+Inputs!$D$41*D6+Inputs!$E$41*G6 -> 2646412.5 | J6: =Inputs!$B$42*B6+Inputs!$C$42*C6+Inputs!$D$42*D6+Inputs!$E$42*G6 -> 1838252.2 | K6: =Inputs!$B$43*B6+Inputs!$C$43*C6+Inputs!$D$43*D6+Inputs!$E$43*G6 -> 2688669.7 | L6: =SQRT(MAX(B6*H6+C6*I6+D6*J6+G6*K6,0)) -> 4376187.8 | M6: =SQRT(MAX(B6^2+D6^2+E6^2+2*Inputs!$D$40*B6*D6+2*Inputs!$E$40*B6*E6+2*Inputs!$E$42*D6*E6,0)) -> 3468959 | N6: =SQRT(MAX(C6^2+F6^2+2*Inputs!$E$41*C6*F6,0)) -> 3054434 | O6: =M6+N6 -> 6523393 | P6: =IF(O6=0,0,1-L6/O6) -> 0.32915466 | Q6: =IF(L6=0,0,B6*H6/L6) -> 1749230.8 | R6: =IF(L6=0,0,C6*I6/L6) -> 1836049.1 | S6: =IF(L6=0,0,D6*J6/L6) -> 277991.83 | T6: =IF(L6=0,0,G6*K6/L6) -> 512916.04 | U6: =Q6+S6+IF(G6=0,0,T6*E6/G6) -> 2497051.1 | V6: =R6+IF(G6=0,0,T6*F6/G6) -> 1879136.7 | W6: =U6+V6-L6 -> 0 | X6: =IF(O6=0,0,L6*M6/O6) -> 2327135 | Y6: =IF(O6=0,0,L6*N6/O6) -> 2049052.8
A7: 1 | B7: =Term!U7 -> 2993750.1 | C7: =Annuity!O7 -> 3071728.5 | D7: =Term!V7 -> 405370.43 | E7: =Term!W7 -> 725853.13 | F7: =Annuity!P7 -> 69454.102 | G7: =E7+F7 -> 795307.23 | H7: =Inputs!$B$40*B7+Inputs!$C$40*C7+Inputs!$D$40*D7+Inputs!$E$40*G7 -> 2424644.8 | I7: =Inputs!$B$41*B7+Inputs!$C$41*C7+Inputs!$D$41*D7+Inputs!$E$41*G7 -> 2623460.4 | J7: =Inputs!$B$42*B7+Inputs!$C$42*C7+Inputs!$D$42*D7+Inputs!$E$42*G7 -> 1570956.2 | K7: =Inputs!$B$43*B7+Inputs!$C$43*C7+Inputs!$D$43*D7+Inputs!$E$43*G7 -> 2514362.1 | L7: =SQRT(MAX(B7*H7+C7*I7+D7*J7+G7*K7,0)) -> 4237198.1 | M7: =SQRT(MAX(B7^2+D7^2+E7^2+2*Inputs!$D$40*B7*D7+2*Inputs!$E$40*B7*E7+2*Inputs!$E$42*D7*E7,0)) -> 3321818.5 | N7: =SQRT(MAX(C7^2+F7^2+2*Inputs!$E$41*C7*F7,0)) -> 3089823.9 | O7: =M7+N7 -> 6411642.4 | P7: =IF(O7=0,0,1-L7/O7) -> 0.33913998 | Q7: =IF(L7=0,0,B7*H7/L7) -> 1713108.6 | R7: =IF(L7=0,0,C7*I7/L7) -> 1901860.1 | S7: =IF(L7=0,0,D7*J7/L7) -> 150292.52 | T7: =IF(L7=0,0,G7*K7/L7) -> 471936.95 | U7: =Q7+S7+IF(G7=0,0,T7*E7/G7) -> 2294123.8 | V7: =R7+IF(G7=0,0,T7*F7/G7) -> 1943074.3 | W7: =U7+V7-L7 -> 0 | X7: =IF(O7=0,0,L7*M7/O7) -> 2195257 | Y7: =IF(O7=0,0,L7*N7/O7) -> 2041941.1
A8: 2 | B8: =Term!U8 -> 2927673.4 | C8: =Annuity!O8 -> 3103455.3 | D8: =Term!V8 -> 186670.21 | E8: =Term!W8 -> 687188.24 | F8: =Annuity!P8 -> 68685.302 | G8: =E8+F8 -> 755873.54 | H8: =Inputs!$B$40*B8+Inputs!$C$40*C8+Inputs!$D$40*D8+Inputs!$E$40*G8 -> 2340778 | I8: =Inputs!$B$41*B8+Inputs!$C$41*C8+Inputs!$D$41*D8+Inputs!$E$41*G8 -> 2607172.9 | J8: =Inputs!$B$42*B8+Inputs!$C$42*C8+Inputs!$D$42*D8+Inputs!$E$42*G8 -> 1340470.8 | K8: =Inputs!$B$43*B8+Inputs!$C$43*C8+Inputs!$D$43*D8+Inputs!$E$43*G8 -> 2356990.8 | L8: =SQRT(MAX(B8*H8+C8*I8+D8*J8+G8*K8,0)) -> 4120205.2 | M8: =SQRT(MAX(B8^2+D8^2+E8^2+2*Inputs!$D$40*B8*D8+2*Inputs!$E$40*B8*E8+2*Inputs!$E$42*D8*E8,0)) -> 3195708.7 | N8: =SQRT(MAX(C8^2+F8^2+2*Inputs!$E$41*C8*F8,0)) -> 3121335.2 | O8: =M8+N8 -> 6317043.9 | P8: =IF(O8=0,0,1-L8/O8) -> 0.34776372 | Q8: =IF(L8=0,0,B8*H8/L8) -> 1663274.8 | R8: =IF(L8=0,0,C8*I8/L8) -> 1963796.5 | S8: =IF(L8=0,0,D8*J8/L8) -> 60731.431 | T8: =IF(L8=0,0,G8*K8/L8) -> 432402.49 | U8: =Q8+S8+IF(G8=0,0,T8*E8/G8) -> 2117116.8 | V8: =R8+IF(G8=0,0,T8*F8/G8) -> 2003088.4 | W8: =U8+V8-L8 -> 0 | X8: =IF(O8=0,0,L8*M8/O8) -> 2084357.2 | Y8: =IF(O8=0,0,L8*N8/O8) -> 2035848.1
A9: 3 | B9: =Term!U9 -> 2856664 | C9: =Annuity!O9 -> 3130840 | D9: =Term!V9 -> 207326.63 | E9: =Term!W9 -> 648695.13 | F9: =Annuity!P9 -> 67821.644 | G9: =E9+F9 -> 716516.78 | H9: =Inputs!$B$40*B9+Inputs!$C$40*C9+Inputs!$D$40*D9+Inputs!$E$40*G9 -> 2253083.2 | I9: =Inputs!$B$41*B9+Inputs!$C$41*C9+Inputs!$D$41*D9+Inputs!$E$41*G9 -> 2647634.8 | J9: =Inputs!$B$42*B9+Inputs!$C$42*C9+Inputs!$D$42*D9+Inputs!$E$42*G9 -> 1348295 | K9: =Inputs!$B$43*B9+Inputs!$C$43*C9+Inputs!$D$43*D9+Inputs!$E$43*G9 -> 2317056.1 | L9: =SQRT(MAX(B9*H9+C9*I9+D9*J9+G9*K9,0)) -> 4082324 | M9: =SQRT(MAX(B9^2+D9^2+E9^2+2*Inputs!$D$40*B9*D9+2*Inputs!$E$40*B9*E9+2*Inputs!$E$42*D9*E9,0)) -> 3112131.5 | N9: =SQRT(MAX(C9^2+F9^2+2*Inputs!$E$41*C9*F9,0)) -> 3148480.3 | O9: =M9+N9 -> 6260611.8 | P9: =IF(O9=0,0,1-L9/O9) -> 0.34793529 | Q9: =IF(L9=0,0,B9*H9/L9) -> 1576626.8 | R9: =IF(L9=0,0,C9*I9/L9) -> 2030539.7 | S9: =IF(L9=0,0,D9*J9/L9) -> 68475.078 | T9: =IF(L9=0,0,G9*K9/L9) -> 406682.46 | U9: =Q9+S9+IF(G9=0,0,T9*E9/G9) -> 2013290 | V9: =R9+IF(G9=0,0,T9*F9/G9) -> 2069034.1 | W9: =U9+V9-L9 -> 0 | X9: =IF(O9=0,0,L9*M9/O9) -> 2029311.1 | Y9: =IF(O9=0,0,L9*N9/O9) -> 2053012.9
A10: 4 | B10: =Term!U10 -> 2780006.6 | C10: =Annuity!O10 -> 3153370.2 | D10: =Term!V10 -> 349307.98 | E10: =Term!W10 -> 610351.96 | F10: =Annuity!P10 -> 66860.159 | G10: =E10+F10 -> 677212.12 | H10: =Inputs!$B$40*B10+Inputs!$C$40*C10+Inputs!$D$40*D10+Inputs!$E$40*G10 -> 2160967.1 | I10: =Inputs!$B$41*B10+Inputs!$C$41*C10+Inputs!$D$41*D10+Inputs!$E$41*G10 -> 2714998.5 | J10: =Inputs!$B$42*B10+Inputs!$C$42*C10+Inputs!$D$42*D10+Inputs!$E$42*G10 -> 1476256.6 | K10: =Inputs!$B$43*B10+Inputs!$C$43*C10+Inputs!$D$43*D10+Inputs!$E$43*G10 -> 2335210.3 | L10: =SQRT(MAX(B10*H10+C10*I10+D10*J10+G10*K10,0)) -> 4082401.1 | M10: =SQRT(MAX(B10^2+D10^2+E10^2+2*Inputs!$D$40*B10*D10+2*Inputs!$E$40*B10*E10+2*Inputs!$E$42*D10*E10,0)) -> 3047059.9 | N10: =SQRT(MAX(C10^2+F10^2+2*Inputs!$E$41*C10*F10,0)) -> 3170746.1 | O10: =M10+N10 -> 6217806.1 | P10: =IF(O10=0,0,1-L10/O10) -> 0.34343383 | Q10: =IF(L10=0,0,B10*H10/L10) -> 1471561.1 | R10: =IF(L10=0,0,C10*I10/L10) -> 2097147 | S10: =IF(L10=0,0,D10*J10/L10) -> 126314.93 | T10: =IF(L10=0,0,G10*K10/L10) -> 387378.08 | U10: =Q10+S10+IF(G10=0,0,T10*E10/G10) -> 1947008.8 | V10: =R10+IF(G10=0,0,T10*F10/G10) -> 2135392.3 | W10: =U10+V10-L10 -> 0 | X10: =IF(O10=0,0,L10*M10/O10) -> 2000596.5 | Y10: =IF(O10=0,0,L10*N10/O10) -> 2081804.7
A11: 5 | B11: =Term!U11 -> 2696946.5 | C11: =Annuity!O11 -> 3170510.8 | D11: =Term!V11 -> 453111.87 | E11: =Term!W11 -> 572136.99 | F11: =Annuity!P11 -> 65798.082 | G11: =E11+F11 -> 637935.07 | H11: =Inputs!$B$40*B11+Inputs!$C$40*C11+Inputs!$D$40*D11+Inputs!$E$40*G11 -> 2063802.6 | I11: =Inputs!$B$41*B11+Inputs!$C$41*C11+Inputs!$D$41*D11+Inputs!$E$41*G11 -> 2769035.9 | J11: =Inputs!$B$42*B11+Inputs!$C$42*C11+Inputs!$D$42*D11+Inputs!$E$42*G11 -> 1564707.1 | K11: =Inputs!$B$43*B11+Inputs!$C$43*C11+Inputs!$D$43*D11+Inputs!$E$43*G11 -> 2331355.3 | L11: =SQRT(MAX(B11*H11+C11*I11+D11*J11+G11*K11,0)) -> 4067119.8 | M11: =SQRT(MAX(B11^2+D11^2+E11^2+2*Inputs!$D$40*B11*D11+2*Inputs!$E$40*B11*E11+2*Inputs!$E$42*D11*E11,0)) -> 2972696.6 | N11: =SQRT(MAX(C11^2+F11^2+2*Inputs!$E$41*C11*F11,0)) -> 3187597 | O11: =M11+N11 -> 6160293.6 | P11: =IF(O11=0,0,1-L11/O11) -> 0.33978474 | Q11: =IF(L11=0,0,B11*H11/L11) -> 1368527.5 | R11: =IF(L11=0,0,C11*I11/L11) -> 2158593.4 | S11: =IF(L11=0,0,D11*J11/L11) -> 174321.73 | T11: =IF(L11=0,0,G11*K11/L11) -> 365677.28 | U11: =Q11+S11+IF(G11=0,0,T11*E11/G11) -> 1870809.7 | V11: =R11+IF(G11=0,0,T11*F11/G11) -> 2196310.2 | W11: =U11+V11-L11 -> 0 | X11: =IF(O11=0,0,L11*M11/O11) -> 1962619.7 | Y11: =IF(O11=0,0,L11*N11/O11) -> 2104500.2
A12: 6 | B12: =Term!U12 -> 2606685.8 | C12: =Annuity!O12 -> 3181707.2 | D12: =Term!V12 -> 522294.69 | E12: =Term!W12 -> 534028.6 | F12: =Annuity!P12 -> 64632.905 | G12: =E12+F12 -> 598661.5 | H12: =Inputs!$B$40*B12+Inputs!$C$40*C12+Inputs!$D$40*D12+Inputs!$E$40*G12 -> 1960924.3 | I12: =Inputs!$B$41*B12+Inputs!$C$41*C12+Inputs!$D$41*D12+Inputs!$E$41*G12 -> 2810274.8 | J12: =Inputs!$B$42*B12+Inputs!$C$42*C12+Inputs!$D$42*D12+Inputs!$E$42*G12 -> 1617052.2 | K12: =Inputs!$B$43*B12+Inputs!$C$43*C12+Inputs!$D$43*D12+Inputs!$E$43*G12 -> 2306907.1 | L12: =SQRT(MAX(B12*H12+C12*I12+D12*J12+G12*K12,0)) -> 4034677.1 | M12: =SQRT(MAX(B12^2+D12^2+E12^2+2*Inputs!$D$40*B12*D12+2*Inputs!$E$40*B12*E12+2*Inputs!$E$42*D12*E12,0)) -> 2885781 | N12: =SQRT(MAX(C12^2+F12^2+2*Inputs!$E$41*C12*F12,0)) -> 3198477.7 | O12: =M12+N12 -> 6084258.7 | P12: =IF(O12=0,0,1-L12/O12) -> 0.33686627 | Q12: =IF(L12=0,0,B12*H12/L12) -> 1266895.3 | R12: =IF(L12=0,0,C12*I12/L12) -> 2216155.4 | S12: =IF(L12=0,0,D12*J12/L12) -> 209329.71 | T12: =IF(L12=0,0,G12*K12/L12) -> 342296.65 | U12: =Q12+S12+IF(G12=0,0,T12*E12/G12) -> 1781566.5 | V12: =R12+IF(G12=0,0,T12*F12/G12) -> 2253110.6 | W12: =U12+V12-L12 -> 0 | X12: =IF(O12=0,0,L12*M12/O12) -> 1913658.7 | Y12: =IF(O12=0,0,L12*N12/O12) -> 2121018.5
A13: 7 | B13: =Term!U13 -> 2508379.8 | C13: =Annuity!O13 -> 3186390.4 | D13: =Term!V13 -> 560435.22 | E13: =Term!W13 -> 496005.31 | F13: =Annuity!P13 -> 63362.441 | G13: =E13+F13 -> 559367.75 | H13: =Inputs!$B$40*B13+Inputs!$C$40*C13+Inputs!$D$40*D13+Inputs!$E$40*G13 -> 1851624.1 | I13: =Inputs!$B$41*B13+Inputs!$C$41*C13+Inputs!$D$41*D13+Inputs!$E$41*G13 -> 2839246.2 | J13: =Inputs!$B$42*B13+Inputs!$C$42*C13+Inputs!$D$42*D13+Inputs!$E$42*G13 -> 1636716.7 | K13: =Inputs!$B$43*B13+Inputs!$C$43*C13+Inputs!$D$43*D13+Inputs!$E$43*G13 -> 2263277.9 | L13: =SQRT(MAX(B13*H13+C13*I13+D13*J13+G13*K13,0)) -> 3984319.5 | M13: =SQRT(MAX(B13^2+D13^2+E13^2+2*Inputs!$D$40*B13*D13+2*Inputs!$E$40*B13*E13+2*Inputs!$E$42*D13*E13,0)) -> 2784266.8 | N13: =SQRT(MAX(C13^2+F13^2+2*Inputs!$E$41*C13*F13,0)) -> 3202818.6 | O13: =M13+N13 -> 5987085.4 | P13: =IF(O13=0,0,1-L13/O13) -> 0.33451435 | Q13: =IF(L13=0,0,B13*H13/L13) -> 1165713.9 | R13: =IF(L13=0,0,C13*I13/L13) -> 2270637.9 | S13: =IF(L13=0,0,D13*J13/L13) -> 230220.92 | T13: =IF(L13=0,0,G13*K13/L13) -> 317746.78 | U13: =Q13+S13+IF(G13=0,0,T13*E13/G13) -> 1677688.8 | V13: =R13+IF(G13=0,0,T13*F13/G13) -> 2306630.7 | W13: =U13+V13-L13 -> 0 | X13: =IF(O13=0,0,L13*M13/O13) -> 1852889.6 | Y13: =IF(O13=0,0,L13*N13/O13) -> 2131429.9
A14: 8 | B14: =Term!U14 -> 2401133.2 | C14: =Annuity!O14 -> 3183982.4 | D14: =Term!V14 -> 571149.99 | E14: =Term!W14 -> 458045.79 | F14: =Annuity!P14 -> 61984.895 | G14: =E14+F14 -> 520030.68 | H14: =Inputs!$B$40*B14+Inputs!$C$40*C14+Inputs!$D$40*D14+Inputs!$E$40*G14 -> 1735145.3 | I14: =Inputs!$B$41*B14+Inputs!$C$41*C14+Inputs!$D$41*D14+Inputs!$E$41*G14 -> 2856494.3 | J14: =Inputs!$B$42*B14+Inputs!$C$42*C14+Inputs!$D$42*D14+Inputs!$E$42*G14 -> 1627160.9 | K14: =Inputs!$B$43*B14+Inputs!$C$43*C14+Inputs!$D$43*D14+Inputs!$E$43*G14 -> 2201884.6 | L14: =SQRT(MAX(B14*H14+C14*I14+D14*J14+G14*K14,0)) -> 3916087.7 | M14: =SQRT(MAX(B14^2+D14^2+E14^2+2*Inputs!$D$40*B14*D14+2*Inputs!$E$40*B14*E14+2*Inputs!$E$42*D14*E14,0)) -> 2667018.2 | N14: =SQRT(MAX(C14^2+F14^2+2*Inputs!$E$41*C14*F14,0)) -> 3200041.5 | O14: =M14+N14 -> 5867059.7 | P14: =IF(O14=0,0,1-L14/O14) -> 0.33252977 | Q14: =IF(L14=0,0,B14*H14/L14) -> 1063897.2 | R14: =IF(L14=0,0,C14*I14/L14) -> 2322478 | S14: =IF(L14=0,0,D14*J14/L14) -> 237316.69 | T14: =IF(L14=0,0,G14*K14/L14) -> 292395.79 | U14: =Q14+S14+IF(G14=0,0,T14*E14/G14) -> 1558757.7 | V14: =R14+IF(G14=0,0,T14*F14/G14) -> 2357330 | W14: =U14+V14-L14 -> 0 | X14: =IF(O14=0,0,L14*M14/O14) -> 1780155.3 | Y14: =IF(O14=0,0,L14*N14/O14) -> 2135932.4
A15: 9 | B15: =Term!U15 -> 2283996 | C15: =Annuity!O15 -> 3173904.3 | D15: =Term!V15 -> 558108.97 | E15: =Term!W15 -> 420128.84 | F15: =Annuity!P15 -> 60498.943 | G15: =E15+F15 -> 480627.79 | H15: =Inputs!$B$40*B15+Inputs!$C$40*C15+Inputs!$D$40*D15+Inputs!$E$40*G15 -> 1610676.8 | I15: =Inputs!$B$41*B15+Inputs!$C$41*C15+Inputs!$D$41*D15+Inputs!$E$41*G15 -> 2862589.5 | J15: =Inputs!$B$42*B15+Inputs!$C$42*C15+Inputs!$D$42*D15+Inputs!$E$42*G15 -> 1591898.9 | K15: =Inputs!$B$43*B15+Inputs!$C$43*C15+Inputs!$D$43*D15+Inputs!$E$43*G15 -> 2124157.3 | L15: =SQRT(MAX(B15*H15+C15*I15+D15*J15+G15*K15,0)) -> 3830632.6 | M15: =SQRT(MAX(B15^2+D15^2+E15^2+2*Inputs!$D$40*B15*D15+2*Inputs!$E$40*B15*E15+2*Inputs!$E$42*D15*E15,0)) -> 2533553.9 | N15: =SQRT(MAX(C15^2+F15^2+2*Inputs!$E$41*C15*F15,0)) -> 3189566.9 | O15: =M15+N15 -> 5723120.8 | P15: =IF(O15=0,0,1-L15/O15) -> 0.33067417 | Q15: =IF(L15=0,0,B15*H15/L15) -> 960358.19 | R15: =IF(L15=0,0,C15*I15/L15) -> 2371823.6 | S15: =IF(L15=0,0,D15*J15/L15) -> 231933.77 | T15: =IF(L15=0,0,G15*K15/L15) -> 266517.08 | U15: =Q15+S15+IF(G15=0,0,T15*E15/G15) -> 1425261.2 | V15: =R15+IF(G15=0,0,T15*F15/G15) -> 2405371.4 | W15: =U15+V15-L15 -> 0 | X15: =IF(O15=0,0,L15*M15/O15) -> 1695773.1 | Y15: =IF(O15=0,0,L15*N15/O15) -> 2134859.6
A16: 10 | B16: =Term!U16 -> 2155958.6 | C16: =Annuity!O16 -> 3155584.7 | D16: =Term!V16 -> 525051.54 | E16: =Term!W16 -> 382233.45 | F16: =Annuity!P16 -> 58903.82 | G16: =E16+F16 -> 441137.27 | H16: =Inputs!$B$40*B16+Inputs!$C$40*C16+Inputs!$D$40*D16+Inputs!$E$40*G16 -> 1477346.8 | I16: =Inputs!$B$41*B16+Inputs!$C$41*C16+Inputs!$D$41*D16+Inputs!$E$41*G16 -> 2858142.3 | J16: =Inputs!$B$42*B16+Inputs!$C$42*C16+Inputs!$D$42*D16+Inputs!$E$42*G16 -> 1534516.4 | K16: =Inputs!$B$43*B16+Inputs!$C$43*C16+Inputs!$D$43*D16+Inputs!$E$43*G16 -> 2031548.9 | L16: =SQRT(MAX(B16*H16+C16*I16+D16*J16+G16*K16,0)) -> 3729088.5 | M16: =SQRT(MAX(B16^2+D16^2+E16^2+2*Inputs!$D$40*B16*D16+2*Inputs!$E$40*B16*E16+2*Inputs!$E$42*D16*E16,0)) -> 2383835.4 | N16: =SQRT(MAX(C16^2+F16^2+2*Inputs!$E$41*C16*F16,0)) -> 3170823.6 | O16: =M16+N16 -> 5554659 | P16: =IF(O16=0,0,1-L16/O16) -> 0.32865574 | Q16: =IF(L16=0,0,B16*H16/L16) -> 854122.55 | R16: =IF(L16=0,0,C16*I16/L16) -> 2418583 | S16: =IF(L16=0,0,D16*J16/L16) -> 216058.21 | T16: =IF(L16=0,0,G16*K16/L16) -> 240324.67 | U16: =Q16+S16+IF(G16=0,0,T16*E16/G16) -> 1278415.5 | V16: =R16+IF(G16=0,0,T16*F16/G16) -> 2450672.9 | W16: =U16+V16-L16 -> 0 | X16: =IF(O16=0,0,L16*M16/O16) -> 1600374.2 | Y16: =IF(O16=0,0,L16*N16/O16) -> 2128714.3
A17: 11 | B17: =Term!U17 -> 2015947.5 | C17: =Annuity!O17 -> 3128471.4 | D17: =Term!V17 -> 475802.92 | E17: =Term!W17 -> 344338.78 | F17: =Annuity!P17 -> 57199.419 | G17: =E17+F17 -> 401538.2 | H17: =Inputs!$B$40*B17+Inputs!$C$40*C17+Inputs!$D$40*D17+Inputs!$E$40*G17 -> 1334214.2 | I17: =Inputs!$B$41*B17+Inputs!$C$41*C17+Inputs!$D$41*D17+Inputs!$E$41*G17 -> 2843819.8 | J17: =Inputs!$B$42*B17+Inputs!$C$42*C17+Inputs!$D$42*D17+Inputs!$E$42*G17 -> 1458689.9 | K17: =Inputs!$B$43*B17+Inputs!$C$43*C17+Inputs!$D$43*D17+Inputs!$E$43*G17 -> 1925544.4 | L17: =SQRT(MAX(B17*H17+C17*I17+D17*J17+G17*K17,0)) -> 3612996.4 | M17: =SQRT(MAX(B17^2+D17^2+E17^2+2*Inputs!$D$40*B17*D17+2*Inputs!$E$40*B17*E17+2*Inputs!$E$42*D17*E17,0)) -> 2218090.1 | N17: =SQRT(MAX(C17^2+F17^2+2*Inputs!$E$41*C17*F17,0)) -> 3143259.2 | O17: =M17+N17 -> 5361349.3 | P17: =IF(O17=0,0,1-L17/O17) -> 0.32610315 | Q17: =IF(L17=0,0,B17*H17/L17) -> 744452.89 | R17: =IF(L17=0,0,C17*I17/L17) -> 2462446.1 | S17: =IF(L17=0,0,D17*J17/L17) -> 192097.86 | T17: =IF(L17=0,0,G17*K17/L17) -> 213999.55 | U17: =Q17+S17+IF(G17=0,0,T17*E17/G17) -> 1120065.9 | V17: =R17+IF(G17=0,0,T17*F17/G17) -> 2492930.5 | W17: =U17+V17-L17 -> 0 | X17: =IF(O17=0,0,L17*M17/O17) -> 1494763.9 | Y17: =IF(O17=0,0,L17*N17/O17) -> 2118232.5
... A25: 19 | B25: =Term!U25 -> 309891.4 | C25: =Annuity!O25 -> 2546838.4 | D25: =Term!V25 -> 0 | E25: =Term!W25 -> 38784.101 | F25: =Annuity!P25 -> 39926.749 | G25: =E25+F25 -> 78710.85 | H25: =Inputs!$B$40*B25+Inputs!$C$40*C25+Inputs!$D$40*D25+Inputs!$E$40*G25 -> -307140.49 | I25: =Inputs!$B$41*B25+Inputs!$C$41*C25+Inputs!$D$41*D25+Inputs!$E$41*G25 -> 2489043.2 | J25: =Inputs!$B$42*B25+Inputs!$C$42*C25+Inputs!$D$42*D25+Inputs!$E$42*G25 -> 676065.02 | K25: =Inputs!$B$43*B25+Inputs!$C$43*C25+Inputs!$D$43*D25+Inputs!$E$43*G25 -> 792893.3 | L25: =SQRT(MAX(B25*H25+C25*I25+D25*J25+G25*K25,0)) -> 2511258.6 | M25: =SQRT(MAX(B25^2+D25^2+E25^2+2*Inputs!$D$40*B25*D25+2*Inputs!$E$40*B25*E25+2*Inputs!$E$42*D25*E25,0)) -> 321786.13 | N25: =SQRT(MAX(C25^2+F25^2+2*Inputs!$E$41*C25*F25,0)) -> 2557112.3 | O25: =M25+N25 -> 2878898.4 | P25: =IF(O25=0,0,1-L25/O25) -> 0.12770155 | Q25: =IF(L25=0,0,B25*H25/L25) -> -37901.39 | R25: =IF(L25=0,0,C25*I25/L25) -> 2524308.2 | S25: =IF(L25=0,0,D25*J25/L25) -> 0 | T25: =IF(L25=0,0,G25*K25/L25) -> 24851.803 | U25: =Q25+S25+IF(G25=0,0,T25*E25/G25) -> -25655.876 | V25: =R25+IF(G25=0,0,T25*F25/G25) -> 2536914.5 | W25: =U25+V25-L25 -> 0 | X25: =IF(O25=0,0,L25*M25/O25) -> 280693.54 | Y25: =IF(O25=0,0,L25*N25/O25) -> 2230565.1
A26: 20 | B26: 0 | C26: =Annuity!O26 -> 2426672.7 | D26: 0 | E26: 0 | F26: =Annuity!P26 -> 37401.387 | G26: =E26+F26 -> 37401.387 | H26: =Inputs!$B$40*B26+Inputs!$C$40*C26+Inputs!$D$40*D26+Inputs!$E$40*G26 -> -597317.84 | I26: =Inputs!$B$41*B26+Inputs!$C$41*C26+Inputs!$D$41*D26+Inputs!$E$41*G26 -> 2436023.1 | J26: =Inputs!$B$42*B26+Inputs!$C$42*C26+Inputs!$D$42*D26+Inputs!$E$42*G26 -> 625368.88 | K26: =Inputs!$B$43*B26+Inputs!$C$43*C26+Inputs!$D$43*D26+Inputs!$E$43*G26 -> 644069.57 | L26: =SQRT(MAX(B26*H26+C26*I26+D26*J26+G26*K26,0)) -> 2436292.2 | M26: =SQRT(MAX(B26^2+D26^2+E26^2+2*Inputs!$D$40*B26*D26+2*Inputs!$E$40*B26*E26+2*Inputs!$E$42*D26*E26,0)) -> 0 | N26: =SQRT(MAX(C26^2+F26^2+2*Inputs!$E$41*C26*F26,0)) -> 2436292.2 | O26: =M26+N26 -> 2436292.2 | P26: =IF(O26=0,0,1-L26/O26) -> 0 | Q26: =IF(L26=0,0,B26*H26/L26) -> 0 | R26: =IF(L26=0,0,C26*I26/L26) -> 2426404.6 | S26: =IF(L26=0,0,D26*J26/L26) -> 0 | T26: =IF(L26=0,0,G26*K26/L26) -> 9887.605 | U26: =Q26+S26+IF(G26=0,0,T26*E26/G26) -> 0 | V26: =R26+IF(G26=0,0,T26*F26/G26) -> 2436292.2 | W26: =U26+V26-L26 -> 0 | X26: =IF(O26=0,0,L26*M26/O26) -> 0 | Y26: =IF(O26=0,0,L26*N26/O26) -> 2436292.2
A27: 21 | B27: 0 | C27: =Annuity!O27 -> 2296940.9 | D27: 0 | E27: 0 | F27: =Annuity!P27 -> 34828.427 | G27: =E27+F27 -> 34828.427 | H27: =Inputs!$B$40*B27+Inputs!$C$40*C27+Inputs!$D$40*D27+Inputs!$E$40*G27 -> -565528.13 | I27: =Inputs!$B$41*B27+Inputs!$C$41*C27+Inputs!$D$41*D27+Inputs!$E$41*G27 -> 2305648 | J27: =Inputs!$B$42*B27+Inputs!$C$42*C27+Inputs!$D$42*D27+Inputs!$E$42*G27 -> 591649.45 | K27: =Inputs!$B$43*B27+Inputs!$C$43*C27+Inputs!$D$43*D27+Inputs!$E$43*G27 -> 609063.66 | L27: =SQRT(MAX(B27*H27+C27*I27+D27*J27+G27*K27,0)) -> 2305894.6 | M27: =SQRT(MAX(B27^2+D27^2+E27^2+2*Inputs!$D$40*B27*D27+2*Inputs!$E$40*B27*E27+2*Inputs!$E$42*D27*E27,0)) -> 0 | N27: =SQRT(MAX(C27^2+F27^2+2*Inputs!$E$41*C27*F27,0)) -> 2305894.6 | O27: =M27+N27 -> 2305894.6 | P27: =IF(O27=0,0,1-L27/O27) -> 0 | Q27: =IF(L27=0,0,B27*H27/L27) -> 0 | R27: =IF(L27=0,0,C27*I27/L27) -> 2296695.3 | S27: =IF(L27=0,0,D27*J27/L27) -> 0 | T27: =IF(L27=0,0,G27*K27/L27) -> 9199.3487 | U27: =Q27+S27+IF(G27=0,0,T27*E27/G27) -> 0 | V27: =R27+IF(G27=0,0,T27*F27/G27) -> 2305894.6 | W27: =U27+V27-L27 -> 0 | X27: =IF(O27=0,0,L27*M27/O27) -> 0 | Y27: =IF(O27=0,0,L27*N27/O27) -> 2305894.6
A28: 22 | B28: 0 | C28: =Annuity!O28 -> 2158497 | D28: 0 | E28: 0 | F28: =Annuity!P28 -> 32222.887 | G28: =E28+F28 -> 32222.887 | H28: =Inputs!$B$40*B28+Inputs!$C$40*C28+Inputs!$D$40*D28+Inputs!$E$40*G28 -> -531568.52 | I28: =Inputs!$B$41*B28+Inputs!$C$41*C28+Inputs!$D$41*D28+Inputs!$E$41*G28 -> 2166552.7 | J28: =Inputs!$B$42*B28+Inputs!$C$42*C28+Inputs!$D$42*D28+Inputs!$E$42*G28 -> 555735.68 | K28: =Inputs!$B$43*B28+Inputs!$C$43*C28+Inputs!$D$43*D28+Inputs!$E$43*G28 -> 571847.13 | L28: =SQRT(MAX(B28*H28+C28*I28+D28*J28+G28*K28,0)) -> 2166777.3 | M28: =SQRT(MAX(B28^2+D28^2+E28^2+2*Inputs!$D$40*B28*D28+2*Inputs!$E$40*B28*E28+2*Inputs!$E$42*D28*E28,0)) -> 0 | N28: =SQRT(MAX(C28^2+F28^2+2*Inputs!$E$41*C28*F28,0)) -> 2166777.3 | O28: =M28+N28 -> 2166777.3 | P28: =IF(O28=0,0,1-L28/O28) -> 0 | Q28: =IF(L28=0,0,B28*H28/L28) -> 0 | R28: =IF(L28=0,0,C28*I28/L28) -> 2158273.2 | S28: =IF(L28=0,0,D28*J28/L28) -> 0 | T28: =IF(L28=0,0,G28*K28/L28) -> 8504.1344 | U28: =Q28+S28+IF(G28=0,0,T28*E28/G28) -> 0 | V28: =R28+IF(G28=0,0,T28*F28/G28) -> 2166777.3 | W28: =U28+V28-L28 -> 0 | X28: =IF(O28=0,0,L28*M28/O28) -> 0 | Y28: =IF(O28=0,0,L28*N28/O28) -> 2166777.3
A29: 23 | B29: 0 | C29: =Annuity!O29 -> 2012437.4 | D29: 0 | E29: 0 | F29: =Annuity!P29 -> 29601.633 | G29: =E29+F29 -> 29601.633 | H29: =Inputs!$B$40*B29+Inputs!$C$40*C29+Inputs!$D$40*D29+Inputs!$E$40*G29 -> -495708.95 | I29: =Inputs!$B$41*B29+Inputs!$C$41*C29+Inputs!$D$41*D29+Inputs!$E$41*G29 -> 2019837.9 | J29: =Inputs!$B$42*B29+Inputs!$C$42*C29+Inputs!$D$42*D29+Inputs!$E$42*G29 -> 517910.18 | K29: =Inputs!$B$43*B29+Inputs!$C$43*C29+Inputs!$D$43*D29+Inputs!$E$43*G29 -> 532710.99 | L29: =SQRT(MAX(B29*H29+C29*I29+D29*J29+G29*K29,0)) -> 2020041.2 | M29: =SQRT(MAX(B29^2+D29^2+E29^2+2*Inputs!$D$40*B29*D29+2*Inputs!$E$40*B29*E29+2*Inputs!$E$42*D29*E29,0)) -> 0 | N29: =SQRT(MAX(C29^2+F29^2+2*Inputs!$E$41*C29*F29,0)) -> 2020041.2 | O29: =M29+N29 -> 2020041.2 | P29: =IF(O29=0,0,1-L29/O29) -> -2.220446e-16 | Q29: =IF(L29=0,0,B29*H29/L29) -> 0 | R29: =IF(L29=0,0,C29*I29/L29) -> 2012234.9 | S29: =IF(L29=0,0,D29*J29/L29) -> 0 | T29: =IF(L29=0,0,G29*K29/L29) -> 7806.3334 | U29: =Q29+S29+IF(G29=0,0,T29*E29/G29) -> 0 | V29: =R29+IF(G29=0,0,T29*F29/G29) -> 2020041.2 | W29: =U29+V29-L29 -> 0 | X29: =IF(O29=0,0,L29*M29/O29) -> 0 | Y29: =IF(O29=0,0,L29*N29/O29) -> 2020041.2
A30: 24 | B30: 0 | C30: =Annuity!O30 -> 1860106.1 | D30: 0 | E30: 0 | F30: =Annuity!P30 -> 26983.28 | G30: =E30+F30 -> 26983.28 | H30: =Inputs!$B$40*B30+Inputs!$C$40*C30+Inputs!$D$40*D30+Inputs!$E$40*G30 -> -458280.7 | I30: =Inputs!$B$41*B30+Inputs!$C$41*C30+Inputs!$D$41*D30+Inputs!$E$41*G30 -> 1866851.9 | J30: =Inputs!$B$42*B30+Inputs!$C$42*C30+Inputs!$D$42*D30+Inputs!$E$42*G30 -> 478518.16 | K30: =Inputs!$B$43*B30+Inputs!$C$43*C30+Inputs!$D$43*D30+Inputs!$E$43*G30 -> 492009.8 | L30: =SQRT(MAX(B30*H30+C30*I30+D30*J30+G30*K30,0)) -> 1867034.7 | M30: =SQRT(MAX(B30^2+D30^2+E30^2+2*Inputs!$D$40*B30*D30+2*Inputs!$E$40*B30*E30+2*Inputs!$E$42*D30*E30,0)) -> 0 | N30: =SQRT(MAX(C30^2+F30^2+2*Inputs!$E$41*C30*F30,0)) -> 1867034.7 | O30: =M30+N30 -> 1867034.7 | P30: =IF(O30=0,0,1-L30/O30) -> 0 | Q30: =IF(L30=0,0,B30*H30/L30) -> 0 | R30: =IF(L30=0,0,C30*I30/L30) -> 1859924 | S30: =IF(L30=0,0,D30*J30/L30) -> 0 | T30: =IF(L30=0,0,G30*K30/L30) -> 7110.7613 | U30: =Q30+S30+IF(G30=0,0,T30*E30/G30) -> 0 | V30: =R30+IF(G30=0,0,T30*F30/G30) -> 1867034.7 | W30: =U30+V30-L30 -> 0 | X30: =IF(O30=0,0,L30*M30/O30) -> 0 | Y30: =IF(O30=0,0,L30*N30/O30) -> 1867034.7
A31: 25 | B31: 0 | C31: =Annuity!O31 -> 1703088.3 | D31: 0 | E31: 0 | F31: =Annuity!P31 -> 24388.022 | G31: =E31+F31 -> 24388.022 | H31: =Inputs!$B$40*B31+Inputs!$C$40*C31+Inputs!$D$40*D31+Inputs!$E$40*G31 -> -419675.07 | I31: =Inputs!$B$41*B31+Inputs!$C$41*C31+Inputs!$D$41*D31+Inputs!$E$41*G31 -> 1709185.3 | J31: =Inputs!$B$42*B31+Inputs!$C$42*C31+Inputs!$D$42*D31+Inputs!$E$42*G31 -> 437966.09 | K31: =Inputs!$B$43*B31+Inputs!$C$43*C31+Inputs!$D$43*D31+Inputs!$E$43*G31 -> 450160.1 | L31: =SQRT(MAX(B31*H31+C31*I31+D31*J31+G31*K31,0)) -> 1709348.4 | M31: =SQRT(MAX(B31^2+D31^2+E31^2+2*Inputs!$D$40*B31*D31+2*Inputs!$E$40*B31*E31+2*Inputs!$E$42*D31*E31,0)) -> 0 | N31: =SQRT(MAX(C31^2+F31^2+2*Inputs!$E$41*C31*F31,0)) -> 1709348.4 | O31: =M31+N31 -> 1709348.4 | P31: =IF(O31=0,0,1-L31/O31) -> 0 | Q31: =IF(L31=0,0,B31*H31/L31) -> 0 | R31: =IF(L31=0,0,C31*I31/L31) -> 1702925.8 | S31: =IF(L31=0,0,D31*J31/L31) -> 0 | T31: =IF(L31=0,0,G31*K31/L31) -> 6422.6311 | U31: =Q31+S31+IF(G31=0,0,T31*E31/G31) -> 0 | V31: =R31+IF(G31=0,0,T31*F31/G31) -> 1709348.4 | W31: =U31+V31-L31 -> 0 | X31: =IF(O31=0,0,L31*M31/O31) -> 0 | Y31: =IF(O31=0,0,L31*N31/O31) -> 1709348.4
A32: 26 | B32: 0 | C32: =Annuity!O32 -> 1543194.2 | D32: 0 | E32: 0 | F32: =Annuity!P32 -> 21837.35 | G32: =E32+F32 -> 21837.35 | H32: =Inputs!$B$40*B32+Inputs!$C$40*C32+Inputs!$D$40*D32+Inputs!$E$40*G32 -> -380339.22 | I32: =Inputs!$B$41*B32+Inputs!$C$41*C32+Inputs!$D$41*D32+Inputs!$E$41*G32 -> 1548653.6 | J32: =Inputs!$B$42*B32+Inputs!$C$42*C32+Inputs!$D$42*D32+Inputs!$E$42*G32 -> 396717.23 | K32: =Inputs!$B$43*B32+Inputs!$C$43*C32+Inputs!$D$43*D32+Inputs!$E$43*G32 -> 407635.91 | L32: =SQRT(MAX(B32*H32+C32*I32+D32*J32+G32*K32,0)) -> 1548797.9 | M32: =SQRT(MAX(B32^2+D32^2+E32^2+2*Inputs!$D$40*B32*D32+2*Inputs!$E$40*B32*E32+2*Inputs!$E$42*D32*E32,0)) -> 0 | N32: =SQRT(MAX(C32^2+F32^2+2*Inputs!$E$41*C32*F32,0)) -> 1548797.9 | O32: =M32+N32 -> 1548797.9 | P32: =IF(O32=0,0,1-L32/O32) -> -2.220446e-16 | Q32: =IF(L32=0,0,B32*H32/L32) -> 0 | R32: =IF(L32=0,0,C32*I32/L32) -> 1543050.4 | S32: =IF(L32=0,0,D32*J32/L32) -> 0 | T32: =IF(L32=0,0,G32*K32/L32) -> 5747.482 | U32: =Q32+S32+IF(G32=0,0,T32*E32/G32) -> 0 | V32: =R32+IF(G32=0,0,T32*F32/G32) -> 1548797.9 | W32: =U32+V32-L32 -> 0 | X32: =IF(O32=0,0,L32*M32/O32) -> 0 | Y32: =IF(O32=0,0,L32*N32/O32) -> 1548797.9
A33: 27 | B33: 0 | C33: =Annuity!O33 -> 1382427.7 | D33: 0 | E33: 0 | F33: =Annuity!P33 -> 19353.662 | G33: =E33+F33 -> 19353.662 | H33: =Inputs!$B$40*B33+Inputs!$C$40*C33+Inputs!$D$40*D33+Inputs!$E$40*G33 -> -340768.52 | I33: =Inputs!$B$41*B33+Inputs!$C$41*C33+Inputs!$D$41*D33+Inputs!$E$41*G33 -> 1387266.1 | J33: =Inputs!$B$42*B33+Inputs!$C$42*C33+Inputs!$D$42*D33+Inputs!$E$42*G33 -> 355283.76 | K33: =Inputs!$B$43*B33+Inputs!$C$43*C33+Inputs!$D$43*D33+Inputs!$E$43*G33 -> 364960.59 | L33: =SQRT(MAX(B33*H33+C33*I33+D33*J33+G33*K33,0)) -> 1387392.7 | M33: =SQRT(MAX(B33^2+D33^2+E33^2+2*Inputs!$D$40*B33*D33+2*Inputs!$E$40*B33*E33+2*Inputs!$E$42*D33*E33,0)) -> 0 | N33: =SQRT(MAX(C33^2+F33^2+2*Inputs!$E$41*C33*F33,0)) -> 1387392.7 | O33: =M33+N33 -> 1387392.7 | P33: =IF(O33=0,0,1-L33/O33) -> 0 | Q33: =IF(L33=0,0,B33*H33/L33) -> 0 | R33: =IF(L33=0,0,C33*I33/L33) -> 1382301.6 | S33: =IF(L33=0,0,D33*J33/L33) -> 0 | T33: =IF(L33=0,0,G33*K33/L33) -> 5091.0776 | U33: =Q33+S33+IF(G33=0,0,T33*E33/G33) -> 0 | V33: =R33+IF(G33=0,0,T33*F33/G33) -> 1387392.7 | W33: =U33+V33-L33 -> 0 | X33: =IF(O33=0,0,L33*M33/O33) -> 0 | Y33: =IF(O33=0,0,L33*N33/O33) -> 1387392.7
A34: 28 | B34: 0 | C34: =Annuity!O34 -> 1222940.3 | D34: 0 | E34: 0 | F34: =Annuity!P34 -> 16959.742 | G34: =E34+F34 -> 16959.742 | H34: =Inputs!$B$40*B34+Inputs!$C$40*C34+Inputs!$D$40*D34+Inputs!$E$40*G34 -> -301495.14 | I34: =Inputs!$B$41*B34+Inputs!$C$41*C34+Inputs!$D$41*D34+Inputs!$E$41*G34 -> 1227180.3 | J34: =Inputs!$B$42*B34+Inputs!$C$42*C34+Inputs!$D$42*D34+Inputs!$E$42*G34 -> 314214.95 | K34: =Inputs!$B$43*B34+Inputs!$C$43*C34+Inputs!$D$43*D34+Inputs!$E$43*G34 -> 322694.82 | L34: =SQRT(MAX(B34*H34+C34*I34+D34*J34+G34*K34,0)) -> 1227290.1 | M34: =SQRT(MAX(B34^2+D34^2+E34^2+2*Inputs!$D$40*B34*D34+2*Inputs!$E$40*B34*E34+2*Inputs!$E$42*D34*E34,0)) -> 0 | N34: =SQRT(MAX(C34^2+F34^2+2*Inputs!$E$41*C34*F34,0)) -> 1227290.1 | O34: =M34+N34 -> 1227290.1 | P34: =IF(O34=0,0,1-L34/O34) -> 0 | Q34: =IF(L34=0,0,B34*H34/L34) -> 0 | R34: =IF(L34=0,0,C34*I34/L34) -> 1222830.8 | S34: =IF(L34=0,0,D34*J34/L34) -> 0 | T34: =IF(L34=0,0,G34*K34/L34) -> 4459.2725 | U34: =Q34+S34+IF(G34=0,0,T34*E34/G34) -> 0 | V34: =R34+IF(G34=0,0,T34*F34/G34) -> 1227290.1 | W34: =U34+V34-L34 -> 0 | X34: =IF(O34=0,0,L34*M34/O34) -> 0 | Y34: =IF(O34=0,0,L34*N34/O34) -> 1227290.1
A35: 29 | B35: 0 | C35: =Annuity!O35 -> 1066968.9 | D35: 0 | E35: 0 | F35: =Annuity!P35 -> 14678.123 | G35: =E35+F35 -> 14678.123 | H35: =Inputs!$B$40*B35+Inputs!$C$40*C35+Inputs!$D$40*D35+Inputs!$E$40*G35 -> -263072.69 | I35: =Inputs!$B$41*B35+Inputs!$C$41*C35+Inputs!$D$41*D35+Inputs!$E$41*G35 -> 1070638.4 | J35: =Inputs!$B$42*B35+Inputs!$C$42*C35+Inputs!$D$42*D35+Inputs!$E$42*G35 -> 274081.28 | K35: =Inputs!$B$43*B35+Inputs!$C$43*C35+Inputs!$D$43*D35+Inputs!$E$43*G35 -> 281420.34 | L35: =SQRT(MAX(B35*H35+C35*I35+D35*J35+G35*K35,0)) -> 1070732.7 | M35: =SQRT(MAX(B35^2+D35^2+E35^2+2*Inputs!$D$40*B35*D35+2*Inputs!$E$40*B35*E35+2*Inputs!$E$42*D35*E35,0)) -> 0 | N35: =SQRT(MAX(C35^2+F35^2+2*Inputs!$E$41*C35*F35,0)) -> 1070732.7 | O35: =M35+N35 -> 1070732.7 | P35: =IF(O35=0,0,1-L35/O35) -> 0 | Q35: =IF(L35=0,0,B35*H35/L35) -> 0 | R35: =IF(L35=0,0,C35*I35/L35) -> 1066874.9 | S35: =IF(L35=0,0,D35*J35/L35) -> 0 | T35: =IF(L35=0,0,G35*K35/L35) -> 3857.8463 | U35: =Q35+S35+IF(G35=0,0,T35*E35/G35) -> 0 | V35: =R35+IF(G35=0,0,T35*F35/G35) -> 1070732.7 | W35: =U35+V35-L35 -> 0 | X35: =IF(O35=0,0,L35*M35/O35) -> 0 | Y35: =IF(O35=0,0,L35*N35/O35) -> 1070732.7
A36: 30 | B36: 0 | C36: =Annuity!O36 -> 916758.18 | D36: 0 | E36: 0 | F36: =Annuity!P36 -> 12530.317 | G36: =E36+F36 -> 12530.317 | H36: =Inputs!$B$40*B36+Inputs!$C$40*C36+Inputs!$D$40*D36+Inputs!$E$40*G36 -> -226056.97 | I36: =Inputs!$B$41*B36+Inputs!$C$41*C36+Inputs!$D$41*D36+Inputs!$E$41*G36 -> 919890.76 | J36: =Inputs!$B$42*B36+Inputs!$C$42*C36+Inputs!$D$42*D36+Inputs!$E$42*G36 -> 235454.7 | K36: =Inputs!$B$43*B36+Inputs!$C$43*C36+Inputs!$D$43*D36+Inputs!$E$43*G36 -> 241719.86 | L36: =SQRT(MAX(B36*H36+C36*I36+D36*J36+G36*K36,0)) -> 919970.76 | M36: =SQRT(MAX(B36^2+D36^2+E36^2+2*Inputs!$D$40*B36*D36+2*Inputs!$E$40*B36*E36+2*Inputs!$E$42*D36*E36,0)) -> 0 | N36: =SQRT(MAX(C36^2+F36^2+2*Inputs!$E$41*C36*F36,0)) -> 919970.76 | O36: =M36+N36 -> 919970.76 | P36: =IF(O36=0,0,1-L36/O36) -> 0 | Q36: =IF(L36=0,0,B36*H36/L36) -> 0 | R36: =IF(L36=0,0,C36*I36/L36) -> 916678.46 | S36: =IF(L36=0,0,D36*J36/L36) -> 0 | T36: =IF(L36=0,0,G36*K36/L36) -> 3292.3074 | U36: =Q36+S36+IF(G36=0,0,T36*E36/G36) -> 0 | V36: =R36+IF(G36=0,0,T36*F36/G36) -> 919970.76 | W36: =U36+V36-L36 -> 0 | X36: =IF(O36=0,0,L36*M36/O36) -> 0 | Y36: =IF(O36=0,0,L36*N36/O36) -> 919970.76
A37: 31 | B37: 0 | C37: =Annuity!O37 -> 774470.35 | D37: 0 | E37: 0 | F37: =Annuity!P37 -> 10535.97 | G37: =E37+F37 -> 10535.97 | H37: =Inputs!$B$40*B37+Inputs!$C$40*C37+Inputs!$D$40*D37+Inputs!$E$40*G37 -> -190983.59 | I37: =Inputs!$B$41*B37+Inputs!$C$41*C37+Inputs!$D$41*D37+Inputs!$E$41*G37 -> 777104.34 | J37: =Inputs!$B$42*B37+Inputs!$C$42*C37+Inputs!$D$42*D37+Inputs!$E$42*G37 -> 198885.57 | K37: =Inputs!$B$43*B37+Inputs!$C$43*C37+Inputs!$D$43*D37+Inputs!$E$43*G37 -> 204153.56 | L37: =SQRT(MAX(B37*H37+C37*I37+D37*J37+G37*K37,0)) -> 777171.29 | M37: =SQRT(MAX(B37^2+D37^2+E37^2+2*Inputs!$D$40*B37*D37+2*Inputs!$E$40*B37*E37+2*Inputs!$E$42*D37*E37,0)) -> 0 | N37: =SQRT(MAX(C37^2+F37^2+2*Inputs!$E$41*C37*F37,0)) -> 777171.29 | O37: =M37+N37 -> 777171.29 | P37: =IF(O37=0,0,1-L37/O37) -> 0 | Q37: =IF(L37=0,0,B37*H37/L37) -> 0 | R37: =IF(L37=0,0,C37*I37/L37) -> 774403.62 | S37: =IF(L37=0,0,D37*J37/L37) -> 0 | T37: =IF(L37=0,0,G37*K37/L37) -> 2767.6727 | U37: =Q37+S37+IF(G37=0,0,T37*E37/G37) -> 0 | V37: =R37+IF(G37=0,0,T37*F37/G37) -> 777171.29 | W37: =U37+V37-L37 -> 0 | X37: =IF(O37=0,0,L37*M37/O37) -> 0 | Y37: =IF(O37=0,0,L37*N37/O37) -> 777171.29
... A50: 44 | B50: 0 | C50: =Annuity!O50 -> 1702.7745 | D50: 0 | E50: 0 | F50: =Annuity!P50 -> 53.437348 | G50: =E50+F50 -> 53.437348 | H50: =Inputs!$B$40*B50+Inputs!$C$40*C50+Inputs!$D$40*D50+Inputs!$E$40*G50 -> -412.33428 | I50: =Inputs!$B$41*B50+Inputs!$C$41*C50+Inputs!$D$41*D50+Inputs!$E$41*G50 -> 1716.1338 | J50: =Inputs!$B$42*B50+Inputs!$C$42*C50+Inputs!$D$42*D50+Inputs!$E$42*G50 -> 452.41229 | K50: =Inputs!$B$43*B50+Inputs!$C$43*C50+Inputs!$D$43*D50+Inputs!$E$43*G50 -> 479.13096 | L50: =SQRT(MAX(B50*H50+C50*I50+D50*J50+G50*K50,0)) -> 1716.9136 | M50: =SQRT(MAX(B50^2+D50^2+E50^2+2*Inputs!$D$40*B50*D50+2*Inputs!$E$40*B50*E50+2*Inputs!$E$42*D50*E50,0)) -> 0 | N50: =SQRT(MAX(C50^2+F50^2+2*Inputs!$E$41*C50*F50,0)) -> 1716.9136 | O50: =M50+N50 -> 1716.9136 | P50: =IF(O50=0,0,1-L50/O50) -> -2.220446e-16 | Q50: =IF(L50=0,0,B50*H50/L50) -> 0 | R50: =IF(L50=0,0,C50*I50/L50) -> 1702.0011 | S50: =IF(L50=0,0,D50*J50/L50) -> 0 | T50: =IF(L50=0,0,G50*K50/L50) -> 14.912508 | U50: =Q50+S50+IF(G50=0,0,T50*E50/G50) -> 0 | V50: =R50+IF(G50=0,0,T50*F50/G50) -> 1716.9136 | W50: =U50+V50-L50 -> 0 | X50: =IF(O50=0,0,L50*M50/O50) -> 0 | Y50: =IF(O50=0,0,L50*N50/O50) -> 1716.9136

Sheet RA
A1: Risk adjustment by backward recursion: RA(t) = CoC × Capital(t) × v + v × RA(t+1)
A2: Capital at the start of year t is held for the year; its cost is paid at the year end, hence the discount factor v.
A5: t | B5: RA: diversified total | C5: RA: term (allocated) | D5: RA: annuity (allocated) | E5: RA: term (standalone) | F5: RA: annuity (standalone) | G5: Cost of capital for year t (PV at t) | H5: Fall in diversified RA over year t | I5: Check: allocated RAs − total | J5: RA: term (proportional) | K5: RA: annuity (proportional)
A6: 0 | B6: =Inputs!$B$5*Capital!L6*(1/(1+Inputs!$B$6))+(1/(1+Inputs!$B$6))*B7 -> 3900670.8 | C6: =Inputs!$B$5*Capital!U6*(1/(1+Inputs!$B$6))+(1/(1+Inputs!$B$6))*C7 -> 1221599 | D6: =Inputs!$B$5*Capital!V6*(1/(1+Inputs!$B$6))+(1/(1+Inputs!$B$6))*D7 -> 2679071.8 | E6: =Inputs!$B$5*Capital!M6*(1/(1+Inputs!$B$6))+(1/(1+Inputs!$B$6))*E7 -> 2120324.1 | F6: =Inputs!$B$5*Capital!N6*(1/(1+Inputs!$B$6))+(1/(1+Inputs!$B$6))*F7 -> 3343105.4 | G6: =Inputs!$B$5*Capital!L6*(1/(1+Inputs!$B$6)) -> 254923.56 | H6: =B6-B7 -> 145551.14 | I6: =C6+D6-B6 -> 0 | J6: =Inputs!$B$5*Capital!X6*(1/(1+Inputs!$B$6))+(1/(1+Inputs!$B$6))*J7 -> 1422131 | K6: =Inputs!$B$5*Capital!Y6*(1/(1+Inputs!$B$6))+(1/(1+Inputs!$B$6))*K7 -> 2478539.8
A7: 1 | B7: =Inputs!$B$5*Capital!L7*(1/(1+Inputs!$B$6))+(1/(1+Inputs!$B$6))*B8 -> 3755119.7 | C7: =Inputs!$B$5*Capital!U7*(1/(1+Inputs!$B$6))+(1/(1+Inputs!$B$6))*C8 -> 1108423.9 | D7: =Inputs!$B$5*Capital!V7*(1/(1+Inputs!$B$6))+(1/(1+Inputs!$B$6))*D8 -> 2646695.8 | E7: =Inputs!$B$5*Capital!M7*(1/(1+Inputs!$B$6))+(1/(1+Inputs!$B$6))*E8 -> 1975796.3 | F7: =Inputs!$B$5*Capital!N7*(1/(1+Inputs!$B$6))+(1/(1+Inputs!$B$6))*F8 -> 3260132.5 | G7: =Inputs!$B$5*Capital!L7*(1/(1+Inputs!$B$6)) -> 246827.08 | H7: =B7-B8 -> 141578.3 | I7: =C7+D7-B7 -> 0 | J7: =Inputs!$B$5*Capital!X7*(1/(1+Inputs!$B$6))+(1/(1+Inputs!$B$6))*J8 -> 1325166.8 | K7: =Inputs!$B$5*Capital!Y7*(1/(1+Inputs!$B$6))+(1/(1+Inputs!$B$6))*K8 -> 2429952.8
A8: 2 | B8: =Inputs!$B$5*Capital!L8*(1/(1+Inputs!$B$6))+(1/(1+Inputs!$B$6))*B9 -> 3613541.4 | C8: =Inputs!$B$5*Capital!U8*(1/(1+Inputs!$B$6))+(1/(1+Inputs!$B$6))*C9 -> 1004029.2 | D8: =Inputs!$B$5*Capital!V8*(1/(1+Inputs!$B$6))+(1/(1+Inputs!$B$6))*D9 -> 2609512.2 | E8: =Inputs!$B$5*Capital!M8*(1/(1+Inputs!$B$6))+(1/(1+Inputs!$B$6))*E9 -> 1835761 | F8: =Inputs!$B$5*Capital!N8*(1/(1+Inputs!$B$6))+(1/(1+Inputs!$B$6))*F9 -> 3172547.1 | G8: =Inputs!$B$5*Capital!L8*(1/(1+Inputs!$B$6)) -> 240011.95 | H8: =B8-B9 -> 138806.07 | I8: =C8+D8-B8 -> 0 | J8: =Inputs!$B$5*Capital!X8*(1/(1+Inputs!$B$6))+(1/(1+Inputs!$B$6))*J9 -> 1233206.4 | K8: =Inputs!$B$5*Capital!Y8*(1/(1+Inputs!$B$6))+(1/(1+Inputs!$B$6))*K9 -> 2380335
A9: 3 | B9: =Inputs!$B$5*Capital!L9*(1/(1+Inputs!$B$6))+(1/(1+Inputs!$B$6))*B10 -> 3474735.3 | C9: =Inputs!$B$5*Capital!U9*(1/(1+Inputs!$B$6))+(1/(1+Inputs!$B$6))*C10 -> 907123.05 | D9: =Inputs!$B$5*Capital!V9*(1/(1+Inputs!$B$6))+(1/(1+Inputs!$B$6))*D10 -> 2567612.3 | E9: =Inputs!$B$5*Capital!M9*(1/(1+Inputs!$B$6))+(1/(1+Inputs!$B$6))*E10 -> 1699091.4 | F9: =Inputs!$B$5*Capital!N9*(1/(1+Inputs!$B$6))+(1/(1+Inputs!$B$6))*F10 -> 3080443.4 | G9: =Inputs!$B$5*Capital!L9*(1/(1+Inputs!$B$6)) -> 237805.28 | H9: =B9-B10 -> 140697.38 | I9: =C9+D9-B9 -> 0 | J9: =Inputs!$B$5*Capital!X9*(1/(1+Inputs!$B$6))+(1/(1+Inputs!$B$6))*J10 -> 1145141.2 | K9: =Inputs!$B$5*Capital!Y9*(1/(1+Inputs!$B$6))+(1/(1+Inputs!$B$6))*K10 -> 2329594.1
A10: 4 | B10: =Inputs!$B$5*Capital!L10*(1/(1+Inputs!$B$6))+(1/(1+Inputs!$B$6))*B11 -> 3334037.9 | C10: =Inputs!$B$5*Capital!U10*(1/(1+Inputs!$B$6))+(1/(1+Inputs!$B$6))*C11 -> 813539.34 | D10: =Inputs!$B$5*Capital!V10*(1/(1+Inputs!$B$6))+(1/(1+Inputs!$B$6))*D11 -> 2520498.6 | E10: =Inputs!$B$5*Capital!M10*(1/(1+Inputs!$B$6))+(1/(1+Inputs!$B$6))*E11 -> 1563336.2 | F10: =Inputs!$B$5*Capital!N10*(1/(1+Inputs!$B$6))+(1/(1+Inputs!$B$6))*F11 -> 2983947.8 | G10: =Inputs!$B$5*Capital!L10*(1/(1+Inputs!$B$6)) -> 237809.78 | H10: =B10-B11 -> 144922.93 | I10: =C10+D10-B10 -> 0 | J10: =Inputs!$B$5*Capital!X10*(1/(1+Inputs!$B$6))+(1/(1+Inputs!$B$6))*J11 -> 1057736.8 | K10: =Inputs!$B$5*Capital!Y10*(1/(1+Inputs!$B$6))+(1/(1+Inputs!$B$6))*K11 -> 2276301.2
A11: 5 | B11: =Inputs!$B$5*Capital!L11*(1/(1+Inputs!$B$6))+(1/(1+Inputs!$B$6))*B12 -> 3189115 | C11: =Inputs!$B$5*Capital!U11*(1/(1+Inputs!$B$6))+(1/(1+Inputs!$B$6))*C12 -> 721124.99 | D11: =Inputs!$B$5*Capital!V11*(1/(1+Inputs!$B$6))+(1/(1+Inputs!$B$6))*D12 -> 2467990 | E11: =Inputs!$B$5*Capital!M11*(1/(1+Inputs!$B$6))+(1/(1+Inputs!$B$6))*E12 -> 1427412.7 | F11: =Inputs!$B$5*Capital!N11*(1/(1+Inputs!$B$6))+(1/(1+Inputs!$B$6))*F12 -> 2883221.5 | G11: =Inputs!$B$5*Capital!L11*(1/(1+Inputs!$B$6)) -> 236919.6 | H11: =B11-B12 -> 148353.74 | I11: =C11+D11-B11 -> 0 | J11: =Inputs!$B$5*Capital!X11*(1/(1+Inputs!$B$6))+(1/(1+Inputs!$B$6))*J12 -> 969433.07 | K11: =Inputs!$B$5*Capital!Y11*(1/(1+Inputs!$B$6))+(1/(1+Inputs!$B$6))*K12 -> 2219681.9
A12: 6 | B12: =Inputs!$B$5*Capital!L12*(1/(1+Inputs!$B$6))+(1/(1+Inputs!$B$6))*B13 -> 3040761.3 | C12: =Inputs!$B$5*Capital!U12*(1/(1+Inputs!$B$6))+(1/(1+Inputs!$B$6))*C13 -> 630510.16 | D12: =Inputs!$B$5*Capital!V12*(1/(1+Inputs!$B$6))+(1/(1+Inputs!$B$6))*D13 -> 2410251.1 | E12: =Inputs!$B$5*Capital!M12*(1/(1+Inputs!$B$6))+(1/(1+Inputs!$B$6))*E13 -> 1291873.3 | F12: =Inputs!$B$5*Capital!N12*(1/(1+Inputs!$B$6))+(1/(1+Inputs!$B$6))*F13 -> 2778462.3 | G12: =Inputs!$B$5*Capital!L12*(1/(1+Inputs!$B$6)) -> 235029.74 | H12: =B12-B13 -> 150857.79 | I12: =C12+D12-B12 -> 0 | J12: =Inputs!$B$5*Capital!X12*(1/(1+Inputs!$B$6))+(1/(1+Inputs!$B$6))*J13 -> 880758.89 | K12: =Inputs!$B$5*Capital!Y12*(1/(1+Inputs!$B$6))+(1/(1+Inputs!$B$6))*K13 -> 2160002.4
A13: 7 | B13: =Inputs!$B$5*Capital!L13*(1/(1+Inputs!$B$6))+(1/(1+Inputs!$B$6))*B14 -> 2889903.5 | C13: =Inputs!$B$5*Capital!U13*(1/(1+Inputs!$B$6))+(1/(1+Inputs!$B$6))*C14 -> 542531.47 | D13: =Inputs!$B$5*Capital!V13*(1/(1+Inputs!$B$6))+(1/(1+Inputs!$B$6))*D14 -> 2347372 | E13: =Inputs!$B$5*Capital!M13*(1/(1+Inputs!$B$6))+(1/(1+Inputs!$B$6))*E14 -> 1157482.6 | F13: =Inputs!$B$5*Capital!N13*(1/(1+Inputs!$B$6))+(1/(1+Inputs!$B$6))*F14 -> 2669907.5 | G13: =Inputs!$B$5*Capital!L13*(1/(1+Inputs!$B$6)) -> 232096.28 | H13: =B13-B14 -> 152362.06 | I13: =C13+D13-B13 -> 0 | J13: =Inputs!$B$5*Capital!X13*(1/(1+Inputs!$B$6))+(1/(1+Inputs!$B$6))*J14 -> 792362.13 | K13: =Inputs!$B$5*Capital!Y13*(1/(1+Inputs!$B$6))+(1/(1+Inputs!$B$6))*K14 -> 2097541.3
A14: 8 | B14: =Inputs!$B$5*Capital!L14*(1/(1+Inputs!$B$6))+(1/(1+Inputs!$B$6))*B15 -> 2737541.4 | C14: =Inputs!$B$5*Capital!U14*(1/(1+Inputs!$B$6))+(1/(1+Inputs!$B$6))*C15 -> 458146.09 | D14: =Inputs!$B$5*Capital!V14*(1/(1+Inputs!$B$6))+(1/(1+Inputs!$B$6))*D15 -> 2279395.3 | E14: =Inputs!$B$5*Capital!M14*(1/(1+Inputs!$B$6))+(1/(1+Inputs!$B$6))*E15 -> 1025151.1 | F14: =Inputs!$B$5*Capital!N14*(1/(1+Inputs!$B$6))+(1/(1+Inputs!$B$6))*F15 -> 2557835.6 | G14: =Inputs!$B$5*Capital!L14*(1/(1+Inputs!$B$6)) -> 228121.61 | H14: =B14-B15 -> 152839.02 | I14: =C14+D14-B14 -> 0 | J14: =Inputs!$B$5*Capital!X14*(1/(1+Inputs!$B$6))+(1/(1+Inputs!$B$6))*J15 -> 704959.62 | K14: =Inputs!$B$5*Capital!Y14*(1/(1+Inputs!$B$6))+(1/(1+Inputs!$B$6))*K15 -> 2032581.8
A15: 9 | B15: =Inputs!$B$5*Capital!L15*(1/(1+Inputs!$B$6))+(1/(1+Inputs!$B$6))*B16 -> 2584702.4 | C15: =Inputs!$B$5*Capital!U15*(1/(1+Inputs!$B$6))+(1/(1+Inputs!$B$6))*C16 -> 378365.01 | D15: =Inputs!$B$5*Capital!V15*(1/(1+Inputs!$B$6))+(1/(1+Inputs!$B$6))*D16 -> 2206337.4 | E15: =Inputs!$B$5*Capital!M15*(1/(1+Inputs!$B$6))+(1/(1+Inputs!$B$6))*E16 -> 895884.53 | F15: =Inputs!$B$5*Capital!N15*(1/(1+Inputs!$B$6))+(1/(1+Inputs!$B$6))*F16 -> 2442568.2 | G15: =Inputs!$B$5*Capital!L15*(1/(1+Inputs!$B$6)) -> 223143.65 | H15: =B15-B16 -> 152296.89 | I15: =C15+D15-B15 -> 0 | J15: =Inputs!$B$5*Capital!X15*(1/(1+Inputs!$B$6))+(1/(1+Inputs!$B$6))*J16 -> 619299.09 | K15: =Inputs!$B$5*Capital!Y15*(1/(1+Inputs!$B$6))+(1/(1+Inputs!$B$6))*K16 -> 1965403.3
A16: 10 | B16: =Inputs!$B$5*Capital!L16*(1/(1+Inputs!$B$6))+(1/(1+Inputs!$B$6))*B17 -> 2432405.5 | C16: =Inputs!$B$5*Capital!U16*(1/(1+Inputs!$B$6))+(1/(1+Inputs!$B$6))*C17 -> 304200.29 | D16: =Inputs!$B$5*Capital!V16*(1/(1+Inputs!$B$6))+(1/(1+Inputs!$B$6))*D17 -> 2128205.2 | E16: =Inputs!$B$5*Capital!M16*(1/(1+Inputs!$B$6))+(1/(1+Inputs!$B$6))*E17 -> 770747.83 | F16: =Inputs!$B$5*Capital!N16*(1/(1+Inputs!$B$6))+(1/(1+Inputs!$B$6))*F17 -> 2324471.3 | G16: =Inputs!$B$5*Capital!L16*(1/(1+Inputs!$B$6)) -> 217228.45 | H16: =B16-B17 -> 150773.14 | I16: =C16+D16-B16 -> 0 | J16: =Inputs!$B$5*Capital!X16*(1/(1+Inputs!$B$6))+(1/(1+Inputs!$B$6))*J17 -> 536131.68 | K16: =Inputs!$B$5*Capital!Y16*(1/(1+Inputs!$B$6))+(1/(1+Inputs!$B$6))*K17 -> 1896273.8
A17: 11 | B17: =Inputs!$B$5*Capital!L17*(1/(1+Inputs!$B$6))+(1/(1+Inputs!$B$6))*B18 -> 2281632.4 | C17: =Inputs!$B$5*Capital!U17*(1/(1+Inputs!$B$6))+(1/(1+Inputs!$B$6))*C18 -> 236621.37 | D17: =Inputs!$B$5*Capital!V17*(1/(1+Inputs!$B$6))+(1/(1+Inputs!$B$6))*D18 -> 2045011 | E17: =Inputs!$B$5*Capital!M17*(1/(1+Inputs!$B$6))+(1/(1+Inputs!$B$6))*E18 -> 650840.14 | F17: =Inputs!$B$5*Capital!N17*(1/(1+Inputs!$B$6))+(1/(1+Inputs!$B$6))*F18 -> 2203956 | G17: =Inputs!$B$5*Capital!L17*(1/(1+Inputs!$B$6)) -> 210465.81 | H17: =B17-B18 -> 148330.82 | I17: =C17+D17-B17 -> 0 | J17: =Inputs!$B$5*Capital!X17*(1/(1+Inputs!$B$6))+(1/(1+Inputs!$B$6))*J18 -> 456193.18 | K17: =Inputs!$B$5*Capital!Y17*(1/(1+Inputs!$B$6))+(1/(1+Inputs!$B$6))*K18 -> 1825439.2
... A50: 44 | B50: =Inputs!$B$5*Capital!L50*(1/(1+Inputs!$B$6))+(1/(1+Inputs!$B$6))*B51 -> 100.01438 | C50: =Inputs!$B$5*Capital!U50*(1/(1+Inputs!$B$6))+(1/(1+Inputs!$B$6))*C51 -> 0 | D50: =Inputs!$B$5*Capital!V50*(1/(1+Inputs!$B$6))+(1/(1+Inputs!$B$6))*D51 -> 100.01438 | E50: =Inputs!$B$5*Capital!M50*(1/(1+Inputs!$B$6))+(1/(1+Inputs!$B$6))*E51 -> 0 | F50: =Inputs!$B$5*Capital!N50*(1/(1+Inputs!$B$6))+(1/(1+Inputs!$B$6))*F51 -> 100.01438 | G50: =Inputs!$B$5*Capital!L50*(1/(1+Inputs!$B$6)) -> 100.01438 | H50: =B50-B51 -> 100.01438 | I50: =C50+D50-B50 -> 0 | J50: =Inputs!$B$5*Capital!X50*(1/(1+Inputs!$B$6))+(1/(1+Inputs!$B$6))*J51 -> 0 | K50: =Inputs!$B$5*Capital!Y50*(1/(1+Inputs!$B$6))+(1/(1+Inputs!$B$6))*K51 -> 100.01438
A51: end | B51: 0 | C51: 0 | D51: 0 | E51: 0 | F51: 0 | J51: 0 | K51: 0

Sheet Factor method
A1: Factor method: calibrate at t = 0, then capital(t) = factor × exposure(t)
A2: Factors use the diversified (Euler) capital at t = 0, so they can be added linearly. RA factor = CoC × capital factor.
A4: Risk | B4: Exposure measure | C4: Exposure at t = 0 | D4: Diversified capital at t = 0 | E4: Capital factor | F4: RA factor (CoC × factor) | G4: PV-summed exposure Σt E(t)·v^(t+1) | H4: RA for this risk
A5: Mortality | B5: Sum assured in force (term) | C5: =Term!X6 -> 2000000000 | D5: =Capital!Q6 -> 1749230.8 | E5: =IF(C5=0,0,D5/C5) -> 0.00087461541 | F5: =Inputs!$B$5*E5 -> 5.2476925e-05 | G5: =SUMPRODUCT(C14:C58,J14:J58) -> 1.9924278e+10 | H5: =F5*G5 -> 1045564.9 | L5: =L13 -> Term’s PV-summed expense exposure | M5: =L14 -> 65254569
A6: Longevity | B6: PV future annuity payments | C6: =Annuity!Q6 -> 60347854 | D6: =Capital!R6 -> 1836049.1 | E6: =IF(C6=0,0,D6/C6) -> 0.030424431 | F6: =Inputs!$B$5*E6 -> 0.0018254658 | G6: =SUMPRODUCT(D14:D58,J14:J58) -> 7.2184712e+08 | H6: =F6*G6 -> 1317707.3 | L6: =K13 -> Annuity’s PV-summed expense exposure | M6: =K14 -> 10318150
A7: Lapse | B7: PV future profits (term) | C7: =Term!Z6 -> 12996781 | D7: =Capital!S6 -> 277991.83 | E7: =IF(C7=0,0,D7/C7) -> 0.021389283 | F7: =Inputs!$B$5*E7 -> 0.001283357 | G7: =SUMPRODUCT(E14:E58,J14:J58) -> 49077891 | H7: =F7*G7 -> 62984.452
A8: Expense | B8: PV future expenses (both groups) | C8: =Term!AA6+Annuity!R6 -> 8348429.4 | D8: =Capital!T6 -> 512916.04 | E8: =IF(C8=0,0,D8/C8) -> 0.061438627 | F8: =Inputs!$B$5*E8 -> 0.0036863176 | G8: =SUMPRODUCT(F14:F58,J14:J58) -> 75572719 | H8: =F8*G8 -> 278585.05 | L8: Term factor RA | M8: =H5+H7+$F$8*M5 -> 1349098.4
A9: RA by factor method | H9: =SUM(H5:H8) -> 2704841.6 | L9: Annuity factor RA | M9: =H6+$F$8*M6 -> 1355743.2
A10: RA by full method (diversified, from RA sheet) | H10: =RA!B6 -> 3900670.8
A11: Factor method error | H11: =IF(H10=0,0,H9/H10-1) -> -0.30657014
A13: t | C13: Exposure: sum assured in force | D13: Exposure: PV annuity payments | E13: Exposure: PV profits | F13: Exposure: PV expenses | G13: Total capital: factor method | H13: Total capital: full method | I13: Factor vs full | J13: Discount factor v^(t+1) | K13: Annuity’s PV-summed expense exposure | L13: Term’s PV-summed expense exposure
A14: 0 | C14: =Term!X6 -> 2000000000 | D14: =Annuity!Q6 -> 60347854 | E14: =Term!Z6 -> 12996781 | F14: =Term!AA6+Annuity!R6 -> 8348429.4 | G14: =$E$5*C14+$E$6*D14+$E$7*E14+$E$8*F14 -> 4376187.8 | H14: =Capital!L6 -> 4376187.8 | I14: =IF(H14=0,0,G14/H14-1) -> 0 | J14: =(1/(1+Inputs!$B$6))^(A14+1) -> 0.97087379 | K14: =SUMPRODUCT(Annuity!R6:R50, J14:J58) -> 10318150 | L14: =SUMPRODUCT(Term!AA6:AA25, J14:J33) -> 65254569
A15: 1 | C15: =Term!X7 -> 1.8990317e+09 | D15: =Annuity!Q7 -> 58573380 | E15: =Term!Z7 -> 10903915 | F15: =Term!AA7+Annuity!R7 -> 7953072.3 | G15: =$E$5*C15+$E$6*D15+$E$7*E15+$E$8*F15 -> 4164836.9 | H15: =Capital!L7 -> 4237198.1 | I15: =IF(H15=0,0,G15/H15-1) -> -0.017077603 | J15: =(1/(1+Inputs!$B$6))^(A15+1) -> 0.94259591 | K15: =SUMPRODUCT(Annuity!R7:R51, J15:J59) -> 9637265.1 | L15: =SUMPRODUCT(Term!AA7:AA26, J15:J34) -> 57830183
A16: 2 | C16: =Term!X8 -> 1.803096e+09 | D16: =Annuity!Q8 -> 56762485 | E16: =Term!Z8 -> 8959401 | F16: =Term!AA8+Annuity!R8 -> 7558735.4 | G16: =$E$5*C16+$E$6*D16+$E$7*E16+$E$8*F16 -> 3960015.3 | H16: =Capital!L8 -> 4120205.2 | I16: =IF(H16=0,0,G16/H16-1) -> -0.038879111 | J16: =(1/(1+Inputs!$B$6))^(A16+1) -> 0.91514166 | K16: =SUMPRODUCT(Annuity!R8:R52, J16:J60) -> 8982593.6 | L16: =SUMPRODUCT(Term!AA8:AA27, J16:J35) -> 50988321
A17: 3 | C17: =Term!X9 -> 1.7119376e+09 | D17: =Annuity!Q9 -> 54915991 | E17: =Term!Z9 -> 7161300.4 | F17: =Term!AA9+Annuity!R9 -> 7165167.8 | G17: =$E$5*C17+$E$6*D17+$E$7*E17+$E$8*F17 -> 3761467.9 | H17: =Capital!L9 -> 4082324 | I17: =IF(H17=0,0,G17/H17-1) -> -0.078596436 | J17: =(1/(1+Inputs!$B$6))^(A17+1) -> 0.88848705 | K17: =SUMPRODUCT(Annuity!R9:R53, J17:J61) -> 8354025.8 | L17: =SUMPRODUCT(Term!AA9:AA28, J17:J36) -> 44699575
A18: 4 | C18: =Term!X10 -> 1.6253141e+09 | D18: =Annuity!Q10 -> 53034961 | E18: =Term!Z10 -> 5508246.9 | F18: =Term!AA10+Annuity!R10 -> 6772121.2 | G18: =$E$5*C18+$E$6*D18+$E$7*E18+$E$8*F18 -> 3568970.5 | H18: =Capital!L10 -> 4082401.1 | I18: =IF(H18=0,0,G18/H18-1) -> -0.12576682 | J18: =(1/(1+Inputs!$B$6))^(A18+1) -> 0.86260878 | K18: =SUMPRODUCT(Annuity!R10:R54, J18:J62) -> 7751439.2 | L18: =SUMPRODUCT(Term!AA10:AA29, J18:J37) -> 38936003
A19: 5 | C19: =Term!X11 -> 1.542995e+09 | D19: =Annuity!Q11 -> 51120725 | E19: =Term!Z11 -> 3999448.7 | F19: =Term!AA11+Annuity!R11 -> 6379350.7 | G19: =$E$5*C19+$E$6*D19+$E$7*E19+$E$8*F19 -> 3382330 | H19: =Capital!L11 -> 4067119.8 | I19: =IF(H19=0,0,G19/H19-1) -> -0.16837217 | J19: =(1/(1+Inputs!$B$6))^(A19+1) -> 0.83748426 | K19: =SUMPRODUCT(Annuity!R11:R55, J19:J63) -> 7174697.6 | L19: =SUMPRODUCT(Term!AA11:AA30, J19:J38) -> 33671053
A20: 6 | C20: =Term!X12 -> 1.4647612e+09 | D20: =Annuity!Q12 -> 49174911 | E20: =Term!Z12 -> 2634694.3 | F20: =Term!AA12+Annuity!R12 -> 5986615 | G20: =$E$5*C20+$E$6*D20+$E$7*E20+$E$8*F20 -> 3201385 | H20: =Capital!L12 -> 4034677.1 | I20: =IF(H20=0,0,G20/H20-1) -> -0.20653255 | J20: =(1/(1+Inputs!$B$6))^(A20+1) -> 0.81309151 | K20: =SUMPRODUCT(Annuity!R12:R56, J20:J64) -> 6623649.1 | L20: =SUMPRODUCT(Term!AA12:AA31, J20:J39) -> 28879496
A21: 7 | C21: =Term!X13 -> 1.3904044e+09 | D21: =Annuity!Q13 -> 47199472 | E21: =Term!Z13 -> 1414359.3 | F21: =Term!AA13+Annuity!R13 -> 5593677.5 | G21: =$E$5*C21+$E$6*D21+$E$7*E21+$E$8*F21 -> 3026006.2 | H21: =Capital!L13 -> 3984319.5 | I21: =IF(H21=0,0,G21/H21-1) -> -0.24052119 | J21: =(1/(1+Inputs!$B$6))^(A21+1) -> 0.78940923 | K21: =SUMPRODUCT(Annuity!R13:R57, J21:J65) -> 6098124.4 | L21: =SUMPRODUCT(Term!AA13:AA32, J21:J40) -> 24537355
A22: 8 | C22: =Term!X14 -> 1.3197266e+09 | D22: =Annuity!Q14 -> 45196728 | E22: =Term!Z14 -> 339415.32 | F22: =Term!AA14+Annuity!R14 -> 5200306.8 | G22: =$E$5*C22+$E$6*D22+$E$7*E22+$E$8*F22 -> 2856097.5 | H22: =Capital!L14 -> 3916087.7 | I22: =IF(H22=0,0,G22/H22-1) -> -0.2706758 | J22: =(1/(1+Inputs!$B$6))^(A22+1) -> 0.76641673 | K22: =SUMPRODUCT(Annuity!R14:R58, J22:J66) -> 5597935.4 | L22: =SUMPRODUCT(Term!AA14:AA33, J22:J41) -> 20621843
A23: 9 | C23: =Term!X15 -> 1.2525396e+09 | D23: =Annuity!Q15 -> 43169392 | E23: =Term!Z15 -> 0 | F23: =Term!AA15+Annuity!R15 -> 4806277.9 | G23: =$E$5*C23+$E$6*D23+$E$7*E23+$E$8*F23 -> 2704185.7 | H23: =Capital!L15 -> 3830632.6 | I23: =IF(H23=0,0,G23/H23-1) -> -0.29406289 | J23: =(1/(1+Inputs!$B$6))^(A23+1) -> 0.74409391 | K23: =SUMPRODUCT(Annuity!R15:R59, J23:J67) -> 5122872.8 | L23: =SUMPRODUCT(Term!AA15:AA34, J23:J42) -> 17111303
A24: 10 | C24: =Term!X16 -> 1.1886643e+09 | D24: =Annuity!Q16 -> 41120611 | E24: =Term!Z16 -> 0 | F24: =Term!AA16+Annuity!R16 -> 4411372.7 | G24: =$E$5*C24+$E$6*D24+$E$7*E24+$E$8*F24 -> 2561724 | H24: =Capital!L16 -> 3729088.5 | I24: =IF(H24=0,0,G24/H24-1) -> -0.31304286 | J24: =(1/(1+Inputs!$B$6))^(A24+1) -> 0.72242128 | K24: =SUMPRODUCT(Annuity!R16:R60, J24:J68) -> 4672703.9 | L24: =SUMPRODUCT(Term!AA16:AA35, J24:J43) -> 13985150
A25: 11 | C25: =Term!X17 -> 1.1279303e+09 | D25: =Annuity!Q17 -> 39054001 | E25: =Term!Z17 -> 0 | F25: =Term!AA17+Annuity!R17 -> 4015382 | G25: =$E$5*C25+$E$6*D25+$E$7*E25+$E$8*F25 -> 2421400.5 | H25: =Capital!L17 -> 3612996.4 | I25: =IF(H25=0,0,G25/H25-1) -> -0.32980822 | J25: =(1/(1+Inputs!$B$6))^(A25+1) -> 0.70137988 | K25: =SUMPRODUCT(Annuity!R17:R61, J25:J69) -> 4247170.2 | L25: =SUMPRODUCT(Term!AA17:AA36, J25:J44) -> 11223814
... A33: 19 | C33: =Term!X25 -> 7.3726769e+08 | D33: =Annuity!Q25 -> 22491328 | E33: =Term!Z25 -> 0 | F33: =Term!AA25+Annuity!R25 -> 787108.5 | G33: =$E$5*C33+$E$6*D33+$E$7*E33+$E$8*F33 -> 1377470.4 | H33: =Capital!L25 -> 2511258.6 | I33: =IF(H33=0,0,G33/H33-1) -> -0.45148206 | J33: =(1/(1+Inputs!$B$6))^(A33+1) -> 0.55367575 | K33: =SUMPRODUCT(Annuity!R25:R69, J33:J77) -> 1688107.1 | L33: =SUMPRODUCT(Term!AA25:AA44, J33:J52) -> 214738.16
A34: 20 | C34: 0 | D34: =Annuity!Q26 -> 20517741 | E34: 0 | F34: =Annuity!R26 -> 374013.87 | G34: =$E$5*C34+$E$6*D34+$E$7*E34+$E$8*F34 -> 647219.48 | H34: =Capital!L26 -> 2436292.2 | I34: =IF(H34=0,0,G34/H34-1) -> -0.73434243 | J34: =(1/(1+Inputs!$B$6))^(A34+1) -> 0.53754928 | K34: =SUMPRODUCT(Annuity!R26:R70, J34:J78) -> 1467042.4 | L34: =SUMPRODUCT(Term!AA26:AA45, J34:J53) -> 0
A35: 21 | C35: 0 | D35: =Annuity!Q27 -> 18593123 | E35: 0 | F35: =Annuity!R27 -> 348284.27 | G35: =$E$5*C35+$E$6*D35+$E$7*E35+$E$8*F35 -> 587083.29 | H35: =Capital!L27 -> 2305894.6 | I35: =IF(H35=0,0,G35/H35-1) -> -0.74539891 | J35: =(1/(1+Inputs!$B$6))^(A35+1) -> 0.5218925 | K35: =SUMPRODUCT(Annuity!R27:R71, J35:J79) -> 1265991.5 | L35: =SUMPRODUCT(Term!AA27:AA46, J35:J54) -> 0
A36: 22 | C36: 0 | D36: =Annuity!Q28 -> 16726943 | E36: 0 | F36: =Annuity!R28 -> 322228.87 | G36: =$E$5*C36+$E$6*D36+$E$7*E36+$E$8*F36 -> 528705.03 | H36: =Capital!L28 -> 2166777.3 | I36: =IF(H36=0,0,G36/H36-1) -> -0.75599476 | J36: =(1/(1+Inputs!$B$6))^(A36+1) -> 0.50669175 | K36: =SUMPRODUCT(Annuity!R28:R72, J36:J80) -> 1084224.6 | L36: =SUMPRODUCT(Term!AA28:AA47, J36:J55) -> 0
A37: 23 | C37: 0 | D37: =Annuity!Q29 -> 14928862 | E37: 0 | F37: =Annuity!R29 -> 296016.33 | G37: =$E$5*C37+$E$6*D37+$E$7*E37+$E$8*F37 -> 472388.96 | H37: =Capital!L29 -> 2020041.2 | I37: =IF(H37=0,0,G37/H37-1) -> -0.76614885 | J37: =(1/(1+Inputs!$B$6))^(A37+1) -> 0.49193374 | K37: =SUMPRODUCT(Annuity!R29:R73, J37:J81) -> 920953.85 | L37: =SUMPRODUCT(Term!AA29:AA48, J37:J56) -> 0
A38: 24 | C38: 0 | D38: =Annuity!Q30 -> 13208553 | E38: 0 | F38: =Annuity!R30 -> 269832.8 | G38: =$E$5*C38+$E$6*D38+$E$7*E38+$E$8*F38 -> 418440.88 | H38: =Capital!L30 -> 1867034.7 | I38: =IF(H38=0,0,G38/H38-1) -> -0.77587944 | J38: =(1/(1+Inputs!$B$6))^(A38+1) -> 0.47760557 | K38: =SUMPRODUCT(Annuity!R30:R74, J38:J82) -> 775333.43 | L38: =SUMPRODUCT(Term!AA30:AA49, J38:J57) -> 0
A39: 25 | C39: 0 | D39: =Annuity!Q31 -> 11575489 | E39: 0 | F39: =Annuity!R31 -> 243880.22 | G39: =$E$5*C39+$E$6*D39+$E$7*E39+$E$8*F39 -> 367161.32 | H39: =Capital!L31 -> 1709348.4 | I39: =IF(H39=0,0,G39/H39-1) -> -0.78520393 | J39: =(1/(1+Inputs!$B$6))^(A39+1) -> 0.46369473 | K39: =SUMPRODUCT(Annuity!R31:R75, J39:J83) -> 646459.78 | L39: =SUMPRODUCT(Term!AA31:AA50, J39:J58) -> 0
A40: 26 | C40: 0 | D40: =Annuity!Q32 -> 10038677 | E40: 0 | F40: =Annuity!R32 -> 218373.5 | G40: =$E$5*C40+$E$6*D40+$E$7*E40+$E$8*F40 -> 318837.6 | H40: =Capital!L32 -> 1548797.9 | I40: =IF(H40=0,0,G40/H40-1) -> -0.79413867 | J40: =(1/(1+Inputs!$B$6))^(A40+1) -> 0.45018906 | K40: =SUMPRODUCT(Annuity!R32:R76, J40:J84) -> 533373.81 | L40: =SUMPRODUCT(Term!AA32:AA51, J40:J59) -> 0
A41: 27 | C41: 0 | D41: =Annuity!Q33 -> 8606373.9 | E41: 0 | F41: =Annuity!R33 -> 193536.62 | G41: =$E$5*C41+$E$6*D41+$E$7*E41+$E$8*F41 -> 273734.65 | H41: =Capital!L33 -> 1387392.7 | I41: =IF(H41=0,0,G41/H41-1) -> -0.80269851 | J41: =(1/(1+Inputs!$B$6))^(A41+1) -> 0.43707675 | K41: =SUMPRODUCT(Annuity!R33:R77, J41:J85) -> 435064.45 | L41: =SUMPRODUCT(Term!AA33:AA52, J41:J60) -> 0
A42: 28 | C42: 0 | D42: =Annuity!Q34 -> 7285763.4 | E42: 0 | F42: =Annuity!R34 -> 169597.42 | G42: =$E$5*C42+$E$6*D42+$E$7*E42+$E$8*F42 -> 232085.04 | H42: =Capital!L34 -> 1227290.1 | I42: =IF(H42=0,0,G42/H42-1) -> -0.81089635 | J42: =(1/(1+Inputs!$B$6))^(A42+1) -> 0.42434636 | K42: =SUMPRODUCT(Annuity!R34:R78, J42:J86) -> 350474.1 | L42: =SUMPRODUCT(Term!AA34:AA53, J42:J61) -> 0
A43: 29 | C43: 0 | D43: =Annuity!Q35 -> 6082625.5 | E43: 0 | F43: =Annuity!R35 -> 146781.23 | G43: =$E$5*C43+$E$6*D43+$E$7*E43+$E$8*F43 -> 194078.46 | H43: =Capital!L35 -> 1070732.7 | I43: =IF(H43=0,0,G43/H43-1) -> -0.81874239 | J43: =(1/(1+Inputs!$B$6))^(A43+1) -> 0.41198676 | K43: =SUMPRODUCT(Annuity!R35:R79, J43:J87) -> 278506.05 | L43: =SUMPRODUCT(Term!AA35:AA54, J43:J62) -> 0
A44: 30 | C44: 0 | D44: =Annuity!Q36 -> 5001008.1 | E44: 0 | F44: =Annuity!R36 -> 125303.17 | G44: =$E$5*C44+$E$6*D44+$E$7*E44+$E$8*F44 -> 159851.28 | H44: =Capital!L36 -> 919970.76 | I44: =IF(H44=0,0,G44/H44-1) -> -0.82624309 | J44: =(1/(1+Inputs!$B$6))^(A44+1) -> 0.39998715 | K44: =SUMPRODUCT(Annuity!R36:R80, J44:J88) -> 218034.12 | L44: =SUMPRODUCT(Term!AA36:AA55, J44:J63) -> 0
A45: 31 | C45: 0 | D45: =Annuity!Q37 -> 4042928.5 | E45: 0 | F45: =Annuity!R37 -> 105359.7 | G45: =$E$5*C45+$E$6*D45+$E$7*E45+$E$8*F45 -> 129476.95 | H45: =Capital!L37 -> 777171.29 | I45: =IF(H45=0,0,G45/H45-1) -> -0.83339972 | J45: =(1/(1+Inputs!$B$6))^(A45+1) -> 0.38833703 | K45: =SUMPRODUCT(Annuity!R37:R81, J45:J89) -> 167914.47 | L45: =SUMPRODUCT(Term!AA37:AA56, J45:J64) -> 0
... A58: 44 | C58: 0 | D58: =Annuity!Q50 -> 10327.326 | E58: 0 | F58: =Annuity!R50 -> 534.37348 | G58: =$E$5*C58+$E$6*D58+$E$7*E58+$E$8*F58 -> 347.03419 | H58: =Capital!L50 -> 1716.9136 | I58: =IF(H58=0,0,G58/H58-1) -> -0.79787323 | J58: =(1/(1+Inputs!$B$6))^(A58+1) -> 0.26443862 | K58: =SUMPRODUCT(Annuity!R50:R94, J58:J102) -> 141.30899 | L58: =SUMPRODUCT(Term!AA50:AA69, J58:J77) -> 0

Sheet Age Bands
A1: Age bands: longevity capital factors banded by attained age
A2: Raw factor = Euler longevity capital ÷ PV annuity exposure; each band uses one capital-weighted factor. Banded RA compared with the full method.
A5: t | B5: Attained Age | C5: Longevity Capital (Euler) | D5: Exposure: PV Annuity (Payments) | E5: Raw Factors | F5: Band | G5: Banded Capital | H5: Discount Factor | K5: Lower Age | L5: Upper Age | M5: Band Factor | N5: Standalone Band Factor | P5: Standalone longevity capital | Q5: Standalone capital, banded
A6: 0 | B6: =Annuity!B6 -> 65 | C6: =Capital!R6 -> 1836049.1 | D6: =Annuity!Q6 -> 60347854 | E6: =IF(D6=0,0,C6/D6) -> 0.030424431 | F6: =INDEX($M$6:$M$13,MATCH(B6,$K$6:$K$13,1)) -> 0.034655116 | G6: =F6*D6 -> 2091361.9 | H6: ='Factor method'!J14 -> 0.97087379 | K6: 65 | L6: 69 | M6: =SUMIFS($C$6:$C$50,$B$6:$B$50,">="&K6,$B$6:$B$50,"<="&L6)/SUMIFS($D$6:$D$50,$B$6:$B$50,">="&K6,$B$6:$B$50,"<="&L6) -> 0.034655116 | N6: =SUMIFS($P$6:$P$50,$B$6:$B$50,">="&K6,$B$6:$B$50,"<="&L6)/SUMIFS($D$6:$D$50,$B$6:$B$50,">="&K6,$B$6:$B$50,"<="&L6) -> 0.054632039 | P6: =Annuity!O6 -> 3036146.4 | Q6: =INDEX($N$6:$N$13,MATCH(B6,$K$6:$K$13,1))*D6 -> 3296926.3
A7: 1 | B7: =Annuity!B7 -> 66 | C7: =Capital!R7 -> 1901860.1 | D7: =Annuity!Q7 -> 58573380 | E7: =IF(D7=0,0,C7/D7) -> 0.0324697 | F7: =INDEX($M$6:$M$13,MATCH(B7,$K$6:$K$13,1)) -> 0.034655116 | G7: =F7*D7 -> 2029867.3 | H7: ='Factor method'!J15 -> 0.94259591 | K7: 70 | L7: 74 | M7: =SUMIFS($C$6:$C$50,$B$6:$B$50,">="&K7,$B$6:$B$50,"<="&L7)/SUMIFS($D$6:$D$50,$B$6:$B$50,">="&K7,$B$6:$B$50,"<="&L7) -> 0.048077797 | N7: =SUMIFS($P$6:$P$50,$B$6:$B$50,">="&K7,$B$6:$B$50,"<="&L7)/SUMIFS($D$6:$D$50,$B$6:$B$50,">="&K7,$B$6:$B$50,"<="&L7) -> 0.067397661 | P7: =Annuity!O7 -> 3071728.5 | Q7: =INDEX($N$6:$N$13,MATCH(B7,$K$6:$K$13,1))*D7 -> 3199983.2
A8: 2 | B8: =Annuity!B8 -> 67 | C8: =Capital!R8 -> 1963796.5 | D8: =Annuity!Q8 -> 56762485 | E8: =IF(D8=0,0,C8/D8) -> 0.034596732 | F8: =INDEX($M$6:$M$13,MATCH(B8,$K$6:$K$13,1)) -> 0.034655116 | G8: =F8*D8 -> 1967110.5 | H8: ='Factor method'!J16 -> 0.91514166 | K8: 75 | L8: 79 | M8: =SUMIFS($C$6:$C$50,$B$6:$B$50,">="&K8,$B$6:$B$50,"<="&L8)/SUMIFS($D$6:$D$50,$B$6:$B$50,">="&K8,$B$6:$B$50,"<="&L8) -> 0.067591792 | N8: =SUMIFS($P$6:$P$50,$B$6:$B$50,">="&K8,$B$6:$B$50,"<="&L8)/SUMIFS($D$6:$D$50,$B$6:$B$50,">="&K8,$B$6:$B$50,"<="&L8) -> 0.083384 | P8: =Annuity!O8 -> 3103455.3 | Q8: =INDEX($N$6:$N$13,MATCH(B8,$K$6:$K$13,1))*D8 -> 3101050.2
A9: 3 | B9: =Annuity!B9 -> 68 | C9: =Capital!R9 -> 2030539.7 | D9: =Annuity!Q9 -> 54915991 | E9: =IF(D9=0,0,C9/D9) -> 0.036975381 | F9: =INDEX($M$6:$M$13,MATCH(B9,$K$6:$K$13,1)) -> 0.034655116 | G9: =F9*D9 -> 1903120 | H9: ='Factor method'!J17 -> 0.88848705 | K9: 80 | L9: 84 | M9: =SUMIFS($C$6:$C$50,$B$6:$B$50,">="&K9,$B$6:$B$50,"<="&L9)/SUMIFS($D$6:$D$50,$B$6:$B$50,">="&K9,$B$6:$B$50,"<="&L9) -> 0.097135677 | N9: =SUMIFS($P$6:$P$50,$B$6:$B$50,">="&K9,$B$6:$B$50,"<="&L9)/SUMIFS($D$6:$D$50,$B$6:$B$50,">="&K9,$B$6:$B$50,"<="&L9) -> 0.10331816 | P9: =Annuity!O9 -> 3130840 | Q9: =INDEX($N$6:$N$13,MATCH(B9,$K$6:$K$13,1))*D9 -> 3000172.5
A10: 4 | B10: =Annuity!B10 -> 69 | C10: =Capital!R10 -> 2097147 | D10: =Annuity!Q10 -> 53034961 | E10: =IF(D10=0,0,C10/D10) -> 0.039542728 | F10: =INDEX($M$6:$M$13,MATCH(B10,$K$6:$K$13,1)) -> 0.034655116 | G10: =F10*D10 -> 1837932.7 | H10: ='Factor method'!J18 -> 0.86260878 | K10: 85 | L10: 89 | M10: =SUMIFS($C$6:$C$50,$B$6:$B$50,">="&K10,$B$6:$B$50,"<="&L10)/SUMIFS($D$6:$D$50,$B$6:$B$50,">="&K10,$B$6:$B$50,"<="&L10) -> 0.12805601 | N10: =SUMIFS($P$6:$P$50,$B$6:$B$50,">="&K10,$B$6:$B$50,"<="&L10)/SUMIFS($D$6:$D$50,$B$6:$B$50,">="&K10,$B$6:$B$50,"<="&L10) -> 0.12806937 | P10: =Annuity!O10 -> 3153370.2 | Q10: =INDEX($N$6:$N$13,MATCH(B10,$K$6:$K$13,1))*D10 -> 2897408
A11: 5 | B11: =Annuity!B11 -> 70 | C11: =Capital!R11 -> 2158593.4 | D11: =Annuity!Q11 -> 51120725 | E11: =IF(D11=0,0,C11/D11) -> 0.042225406 | F11: =INDEX($M$6:$M$13,MATCH(B11,$K$6:$K$13,1)) -> 0.048077797 | G11: =F11*D11 -> 2457771.9 | H11: ='Factor method'!J19 -> 0.83748426 | K11: 90 | L11: 94 | M11: =SUMIFS($C$6:$C$50,$B$6:$B$50,">="&K11,$B$6:$B$50,"<="&L11)/SUMIFS($D$6:$D$50,$B$6:$B$50,">="&K11,$B$6:$B$50,"<="&L11) -> 0.15870965 | N11: =SUMIFS($P$6:$P$50,$B$6:$B$50,">="&K11,$B$6:$B$50,"<="&L11)/SUMIFS($D$6:$D$50,$B$6:$B$50,">="&K11,$B$6:$B$50,"<="&L11) -> 0.15872424 | P11: =Annuity!O11 -> 3170510.8 | Q11: =INDEX($N$6:$N$13,MATCH(B11,$K$6:$K$13,1))*D11 -> 3445417.3
A12: 6 | B12: =Annuity!B12 -> 71 | C12: =Capital!R12 -> 2216155.4 | D12: =Annuity!Q12 -> 49174911 | E12: =IF(D12=0,0,C12/D12) -> 0.045066792 | F12: =INDEX($M$6:$M$13,MATCH(B12,$K$6:$K$13,1)) -> 0.048077797 | G12: =F12*D12 -> 2364221.4 | H12: ='Factor method'!J20 -> 0.81309151 | K12: 95 | L12: 99 | M12: =SUMIFS($C$6:$C$50,$B$6:$B$50,">="&K12,$B$6:$B$50,"<="&L12)/SUMIFS($D$6:$D$50,$B$6:$B$50,">="&K12,$B$6:$B$50,"<="&L12) -> 0.19636551 | N12: =SUMIFS($P$6:$P$50,$B$6:$B$50,">="&K12,$B$6:$B$50,"<="&L12)/SUMIFS($D$6:$D$50,$B$6:$B$50,">="&K12,$B$6:$B$50,"<="&L12) -> 0.19638244 | P12: =Annuity!O12 -> 3181707.2 | Q12: =INDEX($N$6:$N$13,MATCH(B12,$K$6:$K$13,1))*D12 -> 3314273.9
A13: 7 | B13: =Annuity!B13 -> 72 | C13: =Capital!R13 -> 2270637.9 | D13: =Annuity!Q13 -> 47199472 | E13: =IF(D13=0,0,C13/D13) -> 0.048107273 | F13: =INDEX($M$6:$M$13,MATCH(B13,$K$6:$K$13,1)) -> 0.048077797 | G13: =F13*D13 -> 2269246.7 | H13: ='Factor method'!J21 -> 0.78940923 | K13: 100 | L13: 109 | M13: =SUMIFS($C$6:$C$50,$B$6:$B$50,">="&K13,$B$6:$B$50,"<="&L13)/SUMIFS($D$6:$D$50,$B$6:$B$50,">="&K13,$B$6:$B$50,"<="&L13) -> 0.23947369 | N13: =SUMIFS($P$6:$P$50,$B$6:$B$50,">="&K13,$B$6:$B$50,"<="&L13)/SUMIFS($D$6:$D$50,$B$6:$B$50,">="&K13,$B$6:$B$50,"<="&L13) -> 0.23949673 | P13: =Annuity!O13 -> 3186390.4 | Q13: =INDEX($N$6:$N$13,MATCH(B13,$K$6:$K$13,1))*D13 -> 3181134
A14: 8 | B14: =Annuity!B14 -> 73 | C14: =Capital!R14 -> 2322478 | D14: =Annuity!Q14 -> 45196728 | E14: =IF(D14=0,0,C14/D14) -> 0.051385977 | F14: =INDEX($M$6:$M$13,MATCH(B14,$K$6:$K$13,1)) -> 0.048077797 | G14: =F14*D14 -> 2172959.1 | H14: ='Factor method'!J22 -> 0.76641673 | P14: =Annuity!O14 -> 3183982.4 | Q14: =INDEX($N$6:$N$13,MATCH(B14,$K$6:$K$13,1))*D14 -> 3046153.7
A15: 9 | B15: =Annuity!B15 -> 74 | C15: =Capital!R15 -> 2371823.6 | D15: =Annuity!Q15 -> 43169392 | E15: =IF(D15=0,0,C15/D15) -> 0.054942252 | F15: =INDEX($M$6:$M$13,MATCH(B15,$K$6:$K$13,1)) -> 0.048077797 | G15: =F15*D15 -> 2075489.3 | H15: ='Factor method'!J23 -> 0.74409391 | P15: =Annuity!O15 -> 3173904.3 | Q15: =INDEX($N$6:$N$13,MATCH(B15,$K$6:$K$13,1))*D15 -> 2909516
A16: 10 | B16: =Annuity!B16 -> 75 | C16: =Capital!R16 -> 2418583 | D16: =Annuity!Q16 -> 41120611 | E16: =IF(D16=0,0,C16/D16) -> 0.058816806 | F16: =INDEX($M$6:$M$13,MATCH(B16,$K$6:$K$13,1)) -> 0.067591792 | G16: =F16*D16 -> 2779415.8 | H16: ='Factor method'!J24 -> 0.72242128 | K16: Results | P16: =Annuity!O16 -> 3155584.7 | Q16: =INDEX($N$6:$N$13,MATCH(B16,$K$6:$K$13,1))*D16 -> 3428801.1
A17: 11 | B17: =Annuity!B17 -> 76 | C17: =Capital!R17 -> 2462446.1 | D17: =Annuity!Q17 -> 39054001 | E17: =IF(D17=0,0,C17/D17) -> 0.06305234 | F17: =INDEX($M$6:$M$13,MATCH(B17,$K$6:$K$13,1)) -> 0.067591792 | G17: =F17*D17 -> 2639729.9 | H17: ='Factor method'!J25 -> 0.70137988 | K17: Longevity RA (Banded) | L17: =Inputs!B5*SUMPRODUCT('Age Bands'!G6:G50,'Age Bands'!H6:H50) -> 2657940.4 | P17: =Annuity!O17 -> 3128471.4 | Q17: =INDEX($N$6:$N$13,MATCH(B17,$K$6:$K$13,1))*D17 -> 3256478.8
A18: 12 | B18: =Annuity!B18 -> 77 | C18: =Capital!R18 -> 2502870.4 | D18: =Annuity!Q18 -> 36973677 | E18: =IF(D18=0,0,C18/D18) -> 0.067693305 | F18: =INDEX($M$6:$M$13,MATCH(B18,$K$6:$K$13,1)) -> 0.067591792 | G18: =F18*D18 -> 2499117.1 | H18: ='Factor method'!J26 -> 0.68095134 | K18: Total Factor (RA) | L18: ='Factor method'!H9-'Factor method'!H6+'Age Bands'!L17 -> 4045074.7 | P18: =Annuity!O18 -> 3092043.5 | Q18: =INDEX($N$6:$N$13,MATCH(B18,$K$6:$K$13,1))*D18 -> 3083013.1
A19: 13 | B19: =Annuity!B19 -> 78 | C19: =Capital!R19 -> 2539021 | D19: =Annuity!Q19 -> 34884293 | E19: =IF(D19=0,0,C19/D19) -> 0.072784075 | F19: =INDEX($M$6:$M$13,MATCH(B19,$K$6:$K$13,1)) -> 0.067591792 | G19: =F19*D19 -> 2357891.8 | H19: ='Factor method'!J27 -> 0.66111781 | K19: Total RA (full method) | L19: =RA!B6 -> 3900670.8 | P19: =Annuity!O19 -> 3045826.4 | Q19: =INDEX($N$6:$N$13,MATCH(B19,$K$6:$K$13,1))*D19 -> 2908791.9
A20: 14 | B20: =Annuity!B20 -> 79 | C20: =Capital!R20 -> 2569640.7 | D20: =Annuity!Q20 -> 32791062 | E20: =IF(D20=0,0,C20/D20) -> 0.078364059 | F20: =INDEX($M$6:$M$13,MATCH(B20,$K$6:$K$13,1)) -> 0.067591792 | G20: =F20*D20 -> 2216406.6 | H20: ='Factor method'!J28 -> 0.64186195 | K20: Error vs Full Method | L20: =L18/L19-1 -> 0.037020277 | P20: =Annuity!O20 -> 2989408.8 | Q20: =INDEX($N$6:$N$13,MATCH(B20,$K$6:$K$13,1))*D20 -> 2734249.9
A21: 15 | B21: =Annuity!B21 -> 80 | C21: =Capital!R21 -> 2592816.4 | D21: =Annuity!Q21 -> 30699787 | E21: =IF(D21=0,0,C21/D21) -> 0.084457144 | F21: =INDEX($M$6:$M$13,MATCH(B21,$K$6:$K$13,1)) -> 0.097135677 | G21: =F21*D21 -> 2982044.6 | H21: ='Factor method'!J29 -> 0.62316694 | K21: Standalone longevity RA (full) | L21: =Inputs!$B$5*SUMPRODUCT(P6:P50,H6:H50) -> 3327078.6 | P21: =Annuity!O21 -> 2922461.2 | Q21: =INDEX($N$6:$N$13,MATCH(B21,$K$6:$K$13,1))*D21 -> 3171845.4
A22: 16 | B22: =Annuity!B22 -> 81 | C22: =Capital!R22 -> 2605595.7 | D22: =Annuity!Q22 -> 28616872 | E22: =IF(D22=0,0,C22/D22) -> 0.091051028 | F22: =INDEX($M$6:$M$13,MATCH(B22,$K$6:$K$13,1)) -> 0.097135677 | G22: =F22*D22 -> 2779719.3 | H22: ='Factor method'!J30 -> 0.60501645 | K22: Standalone longevity RA (banded) | L22: =Inputs!$B$5*SUMPRODUCT(Q6:Q50,H6:H50) -> 3335403.8 | P22: =Annuity!O22 -> 2844756.7 | Q22: =INDEX($N$6:$N$13,MATCH(B22,$K$6:$K$13,1))*D22 -> 2956642.5
A23: 17 | B23: =Annuity!B23 -> 82 | C23: =Capital!R23 -> 2603428.1 | D23: =Annuity!Q23 -> 26549326 | E23: =IF(D23=0,0,C23/D23) -> 0.098060044 | F23: =INDEX($M$6:$M$13,MATCH(B23,$K$6:$K$13,1)) -> 0.097135677 | G23: =F23*D23 -> 2578886.8 | H23: ='Factor method'!J31 -> 0.58739461 | K23: Error | L23: =L22/L21-1 -> 0.0025022573 | P23: =Annuity!O23 -> 2756192.9 | Q23: =INDEX($N$6:$N$13,MATCH(B23,$K$6:$K$13,1))*D23 -> 2743027.4
A24: 18 | B24: =Annuity!B24 -> 83 | C24: =Capital!R24 -> 2579498.6 | D24: =Annuity!Q24 -> 24504754 | E24: =IF(D24=0,0,C24/D24) -> 0.10526523 | F24: =INDEX($M$6:$M$13,MATCH(B24,$K$6:$K$13,1)) -> 0.097135677 | G24: =F24*D24 -> 2380285.9 | H24: ='Factor method'!J32 -> 0.57028603 | P24: =Annuity!O24 -> 2656814.8 | Q24: =INDEX($N$6:$N$13,MATCH(B24,$K$6:$K$13,1))*D24 -> 2531786
A25: 19 | B25: =Annuity!B25 -> 84 | C25: =Capital!R25 -> 2524308.2 | D25: =Annuity!Q25 -> 22491328 | E25: =IF(D25=0,0,C25/D25) -> 0.11223473 | F25: =INDEX($M$6:$M$13,MATCH(B25,$K$6:$K$13,1)) -> 0.097135677 | G25: =F25*D25 -> 2184710.4 | H25: ='Factor method'!J33 -> 0.55367575 | P25: =Annuity!O25 -> 2546838.4 | Q25: =INDEX($N$6:$N$13,MATCH(B25,$K$6:$K$13,1))*D25 -> 2323762.6
A26: 20 | B26: =Annuity!B26 -> 85 | C26: =Capital!R26 -> 2426404.6 | D26: =Annuity!Q26 -> 20517741 | E26: =IF(D26=0,0,C26/D26) -> 0.11825886 | F26: =INDEX($M$6:$M$13,MATCH(B26,$K$6:$K$13,1)) -> 0.12805601 | G26: =F26*D26 -> 2627420 | H26: ='Factor method'!J34 -> 0.53754928 | P26: =Annuity!O26 -> 2426672.7 | Q26: =INDEX($N$6:$N$13,MATCH(B26,$K$6:$K$13,1))*D26 -> 2627694.2
A27: 21 | B27: =Annuity!B27 -> 86 | C27: =Capital!R27 -> 2296695.3 | D27: =Annuity!Q27 -> 18593123 | E27: =IF(D27=0,0,C27/D27) -> 0.12352391 | F27: =INDEX($M$6:$M$13,MATCH(B27,$K$6:$K$13,1)) -> 0.12805601 | G27: =F27*D27 -> 2380961.2 | H27: ='Factor method'!J35 -> 0.5218925 | P27: =Annuity!O27 -> 2296940.9 | Q27: =INDEX($N$6:$N$13,MATCH(B27,$K$6:$K$13,1))*D27 -> 2381209.6
A28: 22 | B28: =Annuity!B28 -> 87 | C28: =Capital!R28 -> 2158273.2 | D28: =Annuity!Q28 -> 16726943 | E28: =IF(D28=0,0,C28/D28) -> 0.12902974 | F28: =INDEX($M$6:$M$13,MATCH(B28,$K$6:$K$13,1)) -> 0.12805601 | G28: =F28*D28 -> 2141985.6 | H28: ='Factor method'!J36 -> 0.50669175 | P28: =Annuity!O28 -> 2158497 | Q28: =INDEX($N$6:$N$13,MATCH(B28,$K$6:$K$13,1))*D28 -> 2142209.2
A29: 23 | B29: =Annuity!B29 -> 88 | C29: =Capital!R29 -> 2012234.9 | D29: =Annuity!Q29 -> 14928862 | E29: =IF(D29=0,0,C29/D29) -> 0.13478823 | F29: =INDEX($M$6:$M$13,MATCH(B29,$K$6:$K$13,1)) -> 0.12805601 | G29: =F29*D29 -> 1911730.5 | H29: ='Factor method'!J37 -> 0.49193374 | P29: =Annuity!O29 -> 2012437.4 | Q29: =INDEX($N$6:$N$13,MATCH(B29,$K$6:$K$13,1))*D29 -> 1911930
A30: 24 | B30: =Annuity!B30 -> 89 | C30: =Capital!R30 -> 1859924 | D30: =Annuity!Q30 -> 13208553 | E30: =IF(D30=0,0,C30/D30) -> 0.14081209 | F30: =INDEX($M$6:$M$13,MATCH(B30,$K$6:$K$13,1)) -> 0.12805601 | G30: =F30*D30 -> 1691434.7 | H30: ='Factor method'!J38 -> 0.47760557 | P30: =Annuity!O30 -> 1860106.1 | Q30: =INDEX($N$6:$N$13,MATCH(B30,$K$6:$K$13,1))*D30 -> 1691611.2
A31: 25 | B31: =Annuity!B31 -> 90 | C31: =Capital!R31 -> 1702925.8 | D31: =Annuity!Q31 -> 11575489 | E31: =IF(D31=0,0,C31/D31) -> 0.14711481 | F31: =INDEX($M$6:$M$13,MATCH(B31,$K$6:$K$13,1)) -> 0.15870965 | G31: =F31*D31 -> 1837141.8 | H31: ='Factor method'!J39 -> 0.46369473 | P31: =Annuity!O31 -> 1703088.3 | Q31: =INDEX($N$6:$N$13,MATCH(B31,$K$6:$K$13,1))*D31 -> 1837310.6
A32: 26 | B32: =Annuity!B32 -> 91 | C32: =Capital!R32 -> 1543050.4 | D32: =Annuity!Q32 -> 10038677 | E32: =IF(D32=0,0,C32/D32) -> 0.15371053 | F32: =INDEX($M$6:$M$13,MATCH(B32,$K$6:$K$13,1)) -> 0.15870965 | G32: =F32*D32 -> 1593234.9 | H32: ='Factor method'!J40 -> 0.45018906 | P32: =Annuity!O32 -> 1543194.2 | Q32: =INDEX($N$6:$N$13,MATCH(B32,$K$6:$K$13,1))*D32 -> 1593381.4
A33: 27 | B33: =Annuity!B33 -> 92 | C33: =Capital!R33 -> 1382301.6 | D33: =Annuity!Q33 -> 8606373.9 | E33: =IF(D33=0,0,C33/D33) -> 0.16061371 | F33: =INDEX($M$6:$M$13,MATCH(B33,$K$6:$K$13,1)) -> 0.15870965 | G33: =F33*D33 -> 1365914.6 | H33: ='Factor method'!J41 -> 0.43707675 | P33: =Annuity!O33 -> 1382427.7 | Q33: =INDEX($N$6:$N$13,MATCH(B33,$K$6:$K$13,1))*D33 -> 1366040.1
A34: 28 | B34: =Annuity!B34 -> 93 | C34: =Capital!R34 -> 1222830.8 | D34: =Annuity!Q34 -> 7285763.4 | E34: =IF(D34=0,0,C34/D34) -> 0.1678384 | F34: =INDEX($M$6:$M$13,MATCH(B34,$K$6:$K$13,1)) -> 0.15870965 | G34: =F34*D34 -> 1156321 | H34: ='Factor method'!J42 -> 0.42434636 | P34: =Annuity!O34 -> 1222940.3 | Q34: =INDEX($N$6:$N$13,MATCH(B34,$K$6:$K$13,1))*D34 -> 1156427.2
A35: 29 | B35: =Annuity!B35 -> 94 | C35: =Capital!R35 -> 1066874.9 | D35: =Annuity!Q35 -> 6082625.5 | E35: =IF(D35=0,0,C35/D35) -> 0.1753971 | F35: =INDEX($M$6:$M$13,MATCH(B35,$K$6:$K$13,1)) -> 0.15870965 | G35: =F35*D35 -> 965371.36 | H35: ='Factor method'!J43 -> 0.41198676 | P35: =Annuity!O35 -> 1066968.9 | Q35: =INDEX($N$6:$N$13,MATCH(B35,$K$6:$K$13,1))*D35 -> 965460.09
... A50: 44 | B50: =Annuity!B50 -> 109 | C50: =Capital!R50 -> 1702.0011 | D50: =Annuity!Q50 -> 10327.326 | E50: =IF(D50=0,0,C50/D50) -> 0.16480559 | F50: =INDEX($M$6:$M$13,MATCH(B50,$K$6:$K$13,1)) -> 0.23947369 | G50: =F50*D50 -> 2473.1229 | H50: ='Factor method'!J58 -> 0.26443862 | P50: =Annuity!O50 -> 1702.7745 | Q50: =INDEX($N$6:$N$13,MATCH(B50,$K$6:$K$13,1))*D50 -> 2473.3609

Sheet Confidence
A1: Implied confidence level for the IFRS 17 para 119 disclosure
A2: Approximation: treat the year-1 capital as a 99.5% quantile of a normal distribution of outcomes, so σ ≈ capital ÷ 2.576.
A4: One-year view | B4: Capital at t = 0 | C4: σ (approx.) | D4: RA at t = 0 | E4: RA in standard deviations | F4: Implied confidence level
A5: Diversified total | B5: =Capital!L6 -> 4376187.8 | C5: =B5/NORMSINV(0.995) -> 1698943.2 | D5: =RA!B6 -> 3900670.8 | E5: =IF(C5=0,0,D5/C5) -> 2.2959395 | F5: =NORMSDIST(E5) -> 0.98916033
A6: Term (standalone) | B6: =Capital!M6 -> 3468959 | C6: =B6/NORMSINV(0.995) -> 1346734.8 | D6: =RA!E6 -> 2120324.1 | E6: =IF(C6=0,0,D6/C6) -> 1.5744184 | F6: =NORMSDIST(E6) -> 0.94230462
A7: Annuity (standalone) | B7: =Capital!N6 -> 3054434 | C7: =B7/NORMSINV(0.995) -> 1185806.1 | D7: =RA!F6 -> 3343105.4 | E7: =IF(C7=0,0,D7/C7) -> 2.8192682 | F7: =NORMSDIST(E7) -> 0.99759334
A8: Run-off view
A9: Each year's capital is treated as a 99.5% one-year shock (σ_t = capital_t ÷ 2.576), independent across years; σ of the PV over the run-off = √Σ (σ_t × v^t)².
C11: σ over the run-off | D11: RA at t = 0 | E11: RA in standard deviations | F11: Implied confidence level
A12: Diversified total | C12: =SQRT(SUMPRODUCT((Capital!L6:L50/NORMSINV(0.995))^2,'Factor method'!J14:J58^2))*(1+Inputs!$B$6) -> 5267250 | D12: =RA!B6 -> 3900670.8 | E12: =IF(C12=0,0,D12/C12) -> 0.74055167 | F12: =NORMSDIST(E12) -> 0.77051734
A14: Why the two views differ: the one-year view compares the whole RA with a single year's shock, so for long-dated business (annuities) it overstates the confidence level. The run-off view allows for uncertainty building up over the whole run-off, which is closer to how insurers derive the para 119 figure. A full calibration would simulate the distribution.

Sheet Confidence Factor method
A1: Implied confidence level: factor method RA
A2: Same approach as the Confidence sheet, but the RA comes from the factor method (‘Factor method’!H9 for the total, M8/M9 for the groups). One-year view: σ ≈ capital at t = 0 ÷ 2.576 (the 99.5% normal quantile). At t = 0, factor and full-method capital are identical, because the factors are calibrated at t = 0.
A4: One-year view | B4: Capital at t = 0 | C4: σ (approx.) | D4: RA at t = 0 | E4: RA in standard deviations | F4: Implied confidence level
A5: Diversified total | B5: =Capital!L6 -> 4376187.8 | C5: =B5/NORMSINV(0.995) -> 1698943.2 | D5: ='Factor method'!H9 -> 2704841.6 | E5: =IF(C5=0,0,D5/C5) -> 1.592073 | F5: =NORMSDIST(E5) -> 0.94431585
A6: Term (Factored) | B6: =Capital!U6 -> 2497051.1 | C6: =B6/NORMSINV(0.995) -> 969416.36 | D6: ='Factor method'!M8 -> 1349098.4 | E6: =IF(C6=0,0,D6/C6) -> 1.3916604 | F6: =NORMSDIST(E6) -> 0.91798737
A7: Annuity Factored) | B7: =Capital!V6 -> 1879136.7 | C7: =B7/NORMSINV(0.995) -> 729526.88 | D7: ='Factor method'!M9 -> 1355743.2 | E7: =IF(C7=0,0,D7/C7) -> 1.8583869 | F7: =NORMSDIST(E7) -> 0.96844296
A8: Run-off view
A9: Run-off view: σ is deliberately taken from the full-method capital path (Capital!L6:L50), not the factor capital path. σ measures how uncertain the business really is, and that doesn’t change because the RA was calculated with a shortcut. Using the factor capital path would shrink σ as well as the RA, giving a flattering 73.7% instead of 69.6%.
C11: σ over the run-off | D11: RA at t = 0 | E11: RA in standard deviations | F11: Implied confidence level
A12: Diversified total | C12: =SQRT(SUMPRODUCT((Capital!L6:L50/NORMSINV(0.995))^2,'Factor method'!J14:J58^2))*(1+Inputs!$B$6) -> 5267250 | D12: ='Factor method'!H9 -> 2704841.6 | E12: =IF(C12=0,0,D12/C12) -> 0.51352064 | F12: =NORMSDIST(E12) -> 0.69620641
A13: Age Banded Factor | C13: =C12 -> 5267250 | D13: ='Age Bands'!L18 -> 4045074.7 | E13: =IF(C13=0,0,D13/C13) -> 0.7679671 | F13: =NORMSDIST(E13) -> 0.77874664
A15: he factor RA (€2.70m) is about 31% below the full-method RA (€3.90m). Against the true run-off uncertainty, that corresponds to a confidence level of about 70%, against 77% for the full method. Most of the gap comes from the annuity group: one longevity factor calibrated at age 65 understates capital as annuitants age. If an RA is calculated with factors, the disclosed confidence level (para 119) should be checked against an independent measure of risk, not against the factors themselves.
